{
  "generated": "2026-04-29T13:01:44.883633",
  "strategy": "破底翻-ONLY (Top 2, Pure)",
  "period": "2018-04-01 to 2026-03-31",
  "stats": {
    "total_trades": 158,
    "win_rate": 34.177215189873415,
    "avg_pnl": 0.37132911392405055,
    "avg_win": 14.547037037037034,
    "avg_loss": -6.989134615384615,
    "total_return": -45.366298890522174,
    "max_drawdown": 96.89359520257898,
    "avg_hold": 24.924050632911392,
    "exit_reasons": {
      "stop_loss": 92,
      "max_hold": 53,
      "target": 12,
      "end_of_data": 1
    },
    "winning_trades": 54,
    "losing_trades": 104,
    "yearly": {
      "2018": {
        "trades": 6,
        "wins": 0,
        "pnl_sum": -41.83
      },
      "2019": {
        "trades": 18,
        "wins": 10,
        "pnl_sum": 121.41000000000001
      },
      "2020": {
        "trades": 22,
        "wins": 12,
        "pnl_sum": 64.74
      },
      "2021": {
        "trades": 24,
        "wins": 5,
        "pnl_sum": -50.99999999999999
      },
      "2022": {
        "trades": 24,
        "wins": 6,
        "pnl_sum": -29.860000000000017
      },
      "2023": {
        "trades": 18,
        "wins": 1,
        "pnl_sum": -90.82
      },
      "2024": {
        "trades": 22,
        "wins": 5,
        "pnl_sum": -17.089999999999982
      },
      "2025": {
        "trades": 20,
        "wins": 14,
        "pnl_sum": 110.22999999999999
      },
      "2026": {
        "trades": 4,
        "wins": 1,
        "pnl_sum": -7.110000000000002
      }
    }
  },
  "trades": [
    {
      "ticker": "2382.HK",
      "name": "Sunny Optical",
      "signal_date": "2018-10-25",
      "entry_date": "2018-10-26",
      "entry_price": 72.0,
      "exit_date": "2018-10-26",
      "exit_price": 68.45,
      "stop_loss": 68.45,
      "target_price": 164.0,
      "exit_reason": "stop_loss",
      "holding_days": 0,
      "pnl_pct": -4.93,
      "confidence": 0.95,
      "risk_reward": 25.9
    },
    {
      "ticker": "0316.HK",
      "name": "Orient Overseas",
      "signal_date": "2018-10-03",
      "entry_date": "2018-10-04",
      "entry_price": 49.0,
      "exit_date": "2018-10-11",
      "exit_price": 46.75,
      "stop_loss": 46.75,
      "target_price": 82.55,
      "exit_reason": "stop_loss",
      "holding_days": 7,
      "pnl_pct": -4.59,
      "confidence": 0.7,
      "risk_reward": 14.92
    },
    {
      "ticker": "2018.HK",
      "name": "AAC Technologies",
      "signal_date": "2018-11-29",
      "entry_date": "2018-11-30",
      "entry_price": 55.2,
      "exit_date": "2018-12-06",
      "exit_price": 50.78,
      "stop_loss": 50.78,
      "target_price": 101.0,
      "exit_reason": "stop_loss",
      "holding_days": 6,
      "pnl_pct": -8.01,
      "confidence": 0.8,
      "risk_reward": 10.37
    },
    {
      "ticker": "1378.HK",
      "name": "China Hongqiao",
      "signal_date": "2018-11-12",
      "entry_date": "2018-11-13",
      "entry_price": 5.2,
      "exit_date": "2018-11-20",
      "exit_price": 4.86,
      "stop_loss": 4.86,
      "target_price": 8.0,
      "exit_reason": "stop_loss",
      "holding_days": 7,
      "pnl_pct": -6.54,
      "confidence": 0.95,
      "risk_reward": 8.18
    },
    {
      "ticker": "0322.HK",
      "name": "TCL Electronics",
      "signal_date": "2018-12-24",
      "entry_date": "2018-12-27",
      "entry_price": 10.1,
      "exit_date": "2019-01-04",
      "exit_price": 9.68,
      "stop_loss": 9.68,
      "target_price": 18.68,
      "exit_reason": "stop_loss",
      "holding_days": 8,
      "pnl_pct": -4.16,
      "confidence": 0.8,
      "risk_reward": 20.27
    },
    {
      "ticker": "2269.HK",
      "name": "WuXi Biologics",
      "signal_date": "2018-12-07",
      "entry_date": "2018-12-10",
      "entry_price": 19.63,
      "exit_date": "2018-12-10",
      "exit_price": 16.96,
      "stop_loss": 16.96,
      "target_price": 29.92,
      "exit_reason": "stop_loss",
      "holding_days": 0,
      "pnl_pct": -13.6,
      "confidence": 0.78,
      "risk_reward": 3.85
    },
    {
      "ticker": "1810.HK",
      "name": "Xiaomi",
      "signal_date": "2019-01-29",
      "entry_date": "2019-01-30",
      "entry_price": 9.9,
      "exit_date": "2019-03-18",
      "exit_price": 11.9,
      "stop_loss": 9.31,
      "target_price": 16.76,
      "exit_reason": "max_hold",
      "holding_days": 47,
      "pnl_pct": 20.2,
      "confidence": 0.8,
      "risk_reward": 11.67
    },
    {
      "ticker": "2382.HK",
      "name": "Sunny Optical",
      "signal_date": "2019-01-17",
      "entry_date": "2019-01-18",
      "entry_price": 68.2,
      "exit_date": "2019-03-06",
      "exit_price": 99.8,
      "stop_loss": 58.94,
      "target_price": 138.6,
      "exit_reason": "max_hold",
      "holding_days": 47,
      "pnl_pct": 46.33,
      "confidence": 0.8,
      "risk_reward": 7.61
    },
    {
      "ticker": "2018.HK",
      "name": "AAC Technologies",
      "signal_date": "2019-02-04",
      "entry_date": "2019-02-08",
      "entry_price": 46.05,
      "exit_date": "2019-03-22",
      "exit_price": 46.45,
      "stop_loss": 39.07,
      "target_price": 92.35,
      "exit_reason": "max_hold",
      "holding_days": 42,
      "pnl_pct": 0.87,
      "confidence": 0.8,
      "risk_reward": 6.64
    },
    {
      "ticker": "0881.HK",
      "name": "Zhongsheng Group",
      "signal_date": "2019-02-11",
      "entry_date": "2019-02-12",
      "entry_price": 14.58,
      "exit_date": "2019-03-26",
      "exit_price": 19.08,
      "stop_loss": 13.06,
      "target_price": 20.65,
      "exit_reason": "max_hold",
      "holding_days": 42,
      "pnl_pct": 30.86,
      "confidence": 0.8,
      "risk_reward": 3.98
    },
    {
      "ticker": "0316.HK",
      "name": "Orient Overseas",
      "signal_date": "2019-04-23",
      "entry_date": "2019-04-24",
      "entry_price": 50.05,
      "exit_date": "2019-05-02",
      "exit_price": 53.7,
      "stop_loss": 47.09,
      "target_price": 53.7,
      "exit_reason": "target",
      "holding_days": 8,
      "pnl_pct": 7.29,
      "confidence": 0.67,
      "risk_reward": 1.23
    },
    {
      "ticker": "3328.HK",
      "name": "Bank of Communications",
      "signal_date": "2019-05-07",
      "entry_date": "2019-05-08",
      "entry_price": 6.49,
      "exit_date": "2019-05-09",
      "exit_price": 6.16,
      "stop_loss": 6.16,
      "target_price": 6.9,
      "exit_reason": "stop_loss",
      "holding_days": 1,
      "pnl_pct": -5.08,
      "confidence": 0.65,
      "risk_reward": 1.25
    },
    {
      "ticker": "2269.HK",
      "name": "WuXi Biologics",
      "signal_date": "2019-06-18",
      "entry_date": "2019-06-19",
      "entry_price": 23.48,
      "exit_date": "2019-06-25",
      "exit_price": 22.46,
      "stop_loss": 22.46,
      "target_price": 27.95,
      "exit_reason": "stop_loss",
      "holding_days": 6,
      "pnl_pct": -4.34,
      "confidence": 0.88,
      "risk_reward": 4.38
    },
    {
      "ticker": "2020.HK",
      "name": "ANTA Sports",
      "signal_date": "2019-06-17",
      "entry_date": "2019-06-18",
      "entry_price": 50.35,
      "exit_date": "2019-06-25",
      "exit_price": 57.0,
      "stop_loss": 45.07,
      "target_price": 57.0,
      "exit_reason": "target",
      "holding_days": 7,
      "pnl_pct": 13.21,
      "confidence": 0.77,
      "risk_reward": 1.26
    },
    {
      "ticker": "0175.HK",
      "name": "Geely Auto",
      "signal_date": "2019-07-30",
      "entry_date": "2019-07-31",
      "entry_price": 12.1,
      "exit_date": "2019-08-05",
      "exit_price": 11.14,
      "stop_loss": 11.14,
      "target_price": 18.82,
      "exit_reason": "stop_loss",
      "holding_days": 5,
      "pnl_pct": -7.93,
      "confidence": 0.8,
      "risk_reward": 6.97
    },
    {
      "ticker": "0017.HK",
      "name": "New World Dev",
      "signal_date": "2019-07-25",
      "entry_date": "2019-07-26",
      "entry_price": 47.28,
      "exit_date": "2019-07-31",
      "exit_price": 44.16,
      "stop_loss": 44.16,
      "target_price": 55.52,
      "exit_reason": "stop_loss",
      "holding_days": 5,
      "pnl_pct": -6.6,
      "confidence": 0.68,
      "risk_reward": 2.64
    },
    {
      "ticker": "1378.HK",
      "name": "China Hongqiao",
      "signal_date": "2019-08-28",
      "entry_date": "2019-08-29",
      "entry_price": 5.11,
      "exit_date": "2019-10-02",
      "exit_price": 4.81,
      "stop_loss": 4.81,
      "target_price": 6.53,
      "exit_reason": "stop_loss",
      "holding_days": 34,
      "pnl_pct": -5.87,
      "confidence": 0.8,
      "risk_reward": 4.73
    },
    {
      "ticker": "0322.HK",
      "name": "TCL Electronics",
      "signal_date": "2019-08-27",
      "entry_date": "2019-08-28",
      "entry_price": 11.28,
      "exit_date": "2019-09-02",
      "exit_price": 10.69,
      "stop_loss": 10.69,
      "target_price": 13.6,
      "exit_reason": "stop_loss",
      "holding_days": 5,
      "pnl_pct": -5.23,
      "confidence": 0.92,
      "risk_reward": 3.96
    },
    {
      "ticker": "0288.HK",
      "name": "WH Group",
      "signal_date": "2019-09-10",
      "entry_date": "2019-09-11",
      "entry_price": 6.79,
      "exit_date": "2019-10-25",
      "exit_price": 7.65,
      "stop_loss": 5.89,
      "target_price": 9.6,
      "exit_reason": "max_hold",
      "holding_days": 44,
      "pnl_pct": 12.67,
      "confidence": 0.8,
      "risk_reward": 3.14
    },
    {
      "ticker": "1929.HK",
      "name": "Chow Tai Fook",
      "signal_date": "2019-09-09",
      "entry_date": "2019-09-10",
      "entry_price": 6.8,
      "exit_date": "2019-10-16",
      "exit_price": 6.1,
      "stop_loss": 6.1,
      "target_price": 8.76,
      "exit_reason": "stop_loss",
      "holding_days": 36,
      "pnl_pct": -10.29,
      "confidence": 0.82,
      "risk_reward": 2.78
    },
    {
      "ticker": "2018.HK",
      "name": "AAC Technologies",
      "signal_date": "2019-10-02",
      "entry_date": "2019-10-03",
      "entry_price": 41.45,
      "exit_date": "2019-11-08",
      "exit_price": 54.9,
      "stop_loss": 32.21,
      "target_price": 54.9,
      "exit_reason": "target",
      "holding_days": 36,
      "pnl_pct": 32.45,
      "confidence": 0.65,
      "risk_reward": 1.46
    },
    {
      "ticker": "0267.HK",
      "name": "CITIC",
      "signal_date": "2019-10-08",
      "entry_date": "2019-10-09",
      "entry_price": 9.94,
      "exit_date": "2019-11-20",
      "exit_price": 10.16,
      "stop_loss": 8.48,
      "target_price": 11.9,
      "exit_reason": "max_hold",
      "holding_days": 42,
      "pnl_pct": 2.21,
      "confidence": 0.63,
      "risk_reward": 1.34
    },
    {
      "ticker": "0968.HK",
      "name": "Xinyi Solar",
      "signal_date": "2019-11-19",
      "entry_date": "2019-11-20",
      "entry_price": 4.68,
      "exit_date": "2019-12-04",
      "exit_price": 5.2,
      "stop_loss": 4.26,
      "target_price": 5.2,
      "exit_reason": "target",
      "holding_days": 14,
      "pnl_pct": 11.11,
      "confidence": 0.55,
      "risk_reward": 1.25
    },
    {
      "ticker": "0762.HK",
      "name": "China Unicom",
      "signal_date": "2019-12-23",
      "entry_date": "2019-12-24",
      "entry_price": 7.18,
      "exit_date": "2020-02-05",
      "exit_price": 6.43,
      "stop_loss": 6.43,
      "target_price": 8.68,
      "exit_reason": "stop_loss",
      "holding_days": 43,
      "pnl_pct": -10.45,
      "confidence": 0.82,
      "risk_reward": 2.01
    },
    {
      "ticker": "0267.HK",
      "name": "CITIC",
      "signal_date": "2020-01-07",
      "entry_date": "2020-01-08",
      "entry_price": 9.74,
      "exit_date": "2020-01-29",
      "exit_price": 9.41,
      "stop_loss": 9.41,
      "target_price": 10.79,
      "exit_reason": "stop_loss",
      "holding_days": 21,
      "pnl_pct": -3.39,
      "confidence": 0.88,
      "risk_reward": 3.17
    },
    {
      "ticker": "2331.HK",
      "name": "Li Ning",
      "signal_date": "2020-02-26",
      "entry_date": "2020-02-27",
      "entry_price": 21.25,
      "exit_date": "2020-02-28",
      "exit_price": 20.54,
      "stop_loss": 20.54,
      "target_price": 27.7,
      "exit_reason": "stop_loss",
      "holding_days": 1,
      "pnl_pct": -3.34,
      "confidence": 0.8,
      "risk_reward": 9.14
    },
    {
      "ticker": "0291.HK",
      "name": "China Resources Beer",
      "signal_date": "2020-02-26",
      "entry_date": "2020-02-27",
      "entry_price": 36.35,
      "exit_date": "2020-03-12",
      "exit_price": 34.75,
      "stop_loss": 34.75,
      "target_price": 45.2,
      "exit_reason": "stop_loss",
      "holding_days": 14,
      "pnl_pct": -4.4,
      "confidence": 0.95,
      "risk_reward": 5.54
    },
    {
      "ticker": "2319.HK",
      "name": "China Mengniu",
      "signal_date": "2020-03-27",
      "entry_date": "2020-03-30",
      "entry_price": 25.1,
      "exit_date": "2020-05-15",
      "exit_price": 28.2,
      "stop_loss": 24.0,
      "target_price": 32.7,
      "exit_reason": "max_hold",
      "holding_days": 46,
      "pnl_pct": 12.35,
      "confidence": 0.95,
      "risk_reward": 6.91
    },
    {
      "ticker": "0005.HK",
      "name": "HSBC Holdings",
      "signal_date": "2020-03-30",
      "entry_date": "2020-03-31",
      "entry_price": 44.75,
      "exit_date": "2020-04-01",
      "exit_price": 42.05,
      "stop_loss": 42.05,
      "target_price": 61.85,
      "exit_reason": "stop_loss",
      "holding_days": 1,
      "pnl_pct": -6.03,
      "confidence": 0.95,
      "risk_reward": 6.33
    },
    {
      "ticker": "0027.HK",
      "name": "Galaxy Entertainment",
      "signal_date": "2020-04-01",
      "entry_date": "2020-04-02",
      "entry_price": 40.0,
      "exit_date": "2020-05-20",
      "exit_price": 54.0,
      "stop_loss": 37.06,
      "target_price": 62.45,
      "exit_reason": "max_hold",
      "holding_days": 48,
      "pnl_pct": 35.0,
      "confidence": 0.95,
      "risk_reward": 7.63
    },
    {
      "ticker": "1997.HK",
      "name": "Wharf REIC",
      "signal_date": "2020-04-21",
      "entry_date": "2020-04-22",
      "entry_price": 30.25,
      "exit_date": "2020-05-25",
      "exit_price": 27.5,
      "stop_loss": 27.5,
      "target_price": 49.1,
      "exit_reason": "stop_loss",
      "holding_days": 33,
      "pnl_pct": -9.09,
      "confidence": 0.92,
      "risk_reward": 6.86
    },
    {
      "ticker": "0012.HK",
      "name": "Henderson Land",
      "signal_date": "2020-05-05",
      "entry_date": "2020-05-06",
      "entry_price": 30.05,
      "exit_date": "2020-05-25",
      "exit_price": 27.22,
      "stop_loss": 27.22,
      "target_price": 40.55,
      "exit_reason": "stop_loss",
      "holding_days": 19,
      "pnl_pct": -9.42,
      "confidence": 0.78,
      "risk_reward": 3.71
    },
    {
      "ticker": "1928.HK",
      "name": "Sands China",
      "signal_date": "2020-05-05",
      "entry_date": "2020-05-06",
      "entry_price": 30.45,
      "exit_date": "2020-06-17",
      "exit_price": 31.75,
      "stop_loss": 25.1,
      "target_price": 45.0,
      "exit_reason": "max_hold",
      "holding_days": 42,
      "pnl_pct": 4.27,
      "confidence": 0.6,
      "risk_reward": 2.72
    },
    {
      "ticker": "0288.HK",
      "name": "WH Group",
      "signal_date": "2020-06-26",
      "entry_date": "2020-06-29",
      "entry_price": 6.63,
      "exit_date": "2020-08-11",
      "exit_price": 7.22,
      "stop_loss": 6.12,
      "target_price": 7.93,
      "exit_reason": "max_hold",
      "holding_days": 43,
      "pnl_pct": 8.9,
      "confidence": 0.7,
      "risk_reward": 2.53
    },
    {
      "ticker": "2628.HK",
      "name": "China Life",
      "signal_date": "2020-06-24",
      "entry_date": "2020-06-26",
      "entry_price": 15.7,
      "exit_date": "2020-07-06",
      "exit_price": 17.98,
      "stop_loss": 13.5,
      "target_price": 17.98,
      "exit_reason": "target",
      "holding_days": 10,
      "pnl_pct": 14.52,
      "confidence": 0.65,
      "risk_reward": 1.04
    },
    {
      "ticker": "1997.HK",
      "name": "Wharf REIC",
      "signal_date": "2020-07-07",
      "entry_date": "2020-07-08",
      "entry_price": 35.75,
      "exit_date": "2020-08-03",
      "exit_price": 27.02,
      "stop_loss": 27.02,
      "target_price": 49.1,
      "exit_reason": "stop_loss",
      "holding_days": 26,
      "pnl_pct": -24.42,
      "confidence": 0.55,
      "risk_reward": 1.53
    },
    {
      "ticker": "1113.HK",
      "name": "CK Asset Holdings",
      "signal_date": "2020-07-13",
      "entry_date": "2020-07-14",
      "entry_price": 46.0,
      "exit_date": "2020-08-25",
      "exit_price": 42.6,
      "stop_loss": 39.89,
      "target_price": 53.85,
      "exit_reason": "max_hold",
      "holding_days": 42,
      "pnl_pct": -7.39,
      "confidence": 0.63,
      "risk_reward": 1.28
    },
    {
      "ticker": "0005.HK",
      "name": "HSBC Holdings",
      "signal_date": "2020-08-20",
      "entry_date": "2020-08-21",
      "entry_price": 33.65,
      "exit_date": "2020-09-17",
      "exit_price": 31.49,
      "stop_loss": 31.49,
      "target_price": 54.4,
      "exit_reason": "stop_loss",
      "holding_days": 27,
      "pnl_pct": -6.42,
      "confidence": 0.8,
      "risk_reward": 9.6
    },
    {
      "ticker": "0003.HK",
      "name": "HK & China Gas",
      "signal_date": "2020-08-25",
      "entry_date": "2020-08-26",
      "entry_price": 10.61,
      "exit_date": "2020-10-09",
      "exit_price": 10.67,
      "stop_loss": 9.93,
      "target_price": 13.86,
      "exit_reason": "max_hold",
      "holding_days": 44,
      "pnl_pct": 0.53,
      "confidence": 0.8,
      "risk_reward": 4.78
    },
    {
      "ticker": "0981.HK",
      "name": "SMIC",
      "signal_date": "2020-09-24",
      "entry_date": "2020-09-25",
      "entry_price": 19.46,
      "exit_date": "2020-09-28",
      "exit_price": 17.51,
      "stop_loss": 17.51,
      "target_price": 41.95,
      "exit_reason": "stop_loss",
      "holding_days": 3,
      "pnl_pct": -10.02,
      "confidence": 0.88,
      "risk_reward": 11.54
    },
    {
      "ticker": "0027.HK",
      "name": "Galaxy Entertainment",
      "signal_date": "2020-10-29",
      "entry_date": "2020-10-30",
      "entry_price": 52.5,
      "exit_date": "2020-11-10",
      "exit_price": 62.8,
      "stop_loss": 49.01,
      "target_price": 62.8,
      "exit_reason": "target",
      "holding_days": 11,
      "pnl_pct": 19.62,
      "confidence": 0.7,
      "risk_reward": 2.95
    },
    {
      "ticker": "0291.HK",
      "name": "China Resources Beer",
      "signal_date": "2020-10-27",
      "entry_date": "2020-10-28",
      "entry_price": 48.0,
      "exit_date": "2020-11-11",
      "exit_price": 54.45,
      "stop_loss": 43.97,
      "target_price": 54.45,
      "exit_reason": "target",
      "holding_days": 14,
      "pnl_pct": 13.44,
      "confidence": 0.65,
      "risk_reward": 1.6
    },
    {
      "ticker": "1044.HK",
      "name": "Hengan International",
      "signal_date": "2020-11-20",
      "entry_date": "2020-11-23",
      "entry_price": 57.25,
      "exit_date": "2021-01-06",
      "exit_price": 57.45,
      "stop_loss": 50.45,
      "target_price": 71.0,
      "exit_reason": "max_hold",
      "holding_days": 44,
      "pnl_pct": 0.35,
      "confidence": 0.82,
      "risk_reward": 2.02
    },
    {
      "ticker": "0005.HK",
      "name": "HSBC Holdings",
      "signal_date": "2020-11-02",
      "entry_date": "2020-11-03",
      "entry_price": 33.2,
      "exit_date": "2020-11-25",
      "exit_price": 41.0,
      "stop_loss": 27.07,
      "target_price": 41.0,
      "exit_reason": "target",
      "holding_days": 22,
      "pnl_pct": 23.49,
      "confidence": 0.67,
      "risk_reward": 1.27
    },
    {
      "ticker": "1177.HK",
      "name": "Sino Biopharmaceutical",
      "signal_date": "2020-12-15",
      "entry_date": "2020-12-16",
      "entry_price": 7.18,
      "exit_date": "2021-01-29",
      "exit_price": 7.23,
      "stop_loss": 6.38,
      "target_price": 10.88,
      "exit_reason": "max_hold",
      "holding_days": 44,
      "pnl_pct": 0.7,
      "confidence": 0.95,
      "risk_reward": 4.65
    },
    {
      "ticker": "0322.HK",
      "name": "TCL Electronics",
      "signal_date": "2020-12-17",
      "entry_date": "2020-12-18",
      "entry_price": 13.3,
      "exit_date": "2021-01-28",
      "exit_price": 15.36,
      "stop_loss": 12.33,
      "target_price": 15.36,
      "exit_reason": "target",
      "holding_days": 41,
      "pnl_pct": 15.49,
      "confidence": 0.6,
      "risk_reward": 2.12
    },
    {
      "ticker": "0762.HK",
      "name": "China Unicom",
      "signal_date": "2021-01-26",
      "entry_date": "2021-01-27",
      "entry_price": 4.53,
      "exit_date": "2021-03-12",
      "exit_price": 4.63,
      "stop_loss": 4.14,
      "target_price": 6.53,
      "exit_reason": "max_hold",
      "holding_days": 44,
      "pnl_pct": 2.21,
      "confidence": 0.95,
      "risk_reward": 5.1
    },
    {
      "ticker": "0941.HK",
      "name": "China Mobile",
      "signal_date": "2021-01-26",
      "entry_date": "2021-01-27",
      "entry_price": 46.1,
      "exit_date": "2021-03-12",
      "exit_price": 52.0,
      "stop_loss": 39.84,
      "target_price": 59.85,
      "exit_reason": "max_hold",
      "holding_days": 44,
      "pnl_pct": 12.8,
      "confidence": 0.82,
      "risk_reward": 2.2
    },
    {
      "ticker": "1876.HK",
      "name": "Budweiser APAC",
      "signal_date": "2021-02-08",
      "entry_date": "2021-02-09",
      "entry_price": 24.25,
      "exit_date": "2021-03-04",
      "exit_price": 23.18,
      "stop_loss": 23.18,
      "target_price": 29.15,
      "exit_reason": "stop_loss",
      "holding_days": 23,
      "pnl_pct": -4.41,
      "confidence": 0.8,
      "risk_reward": 4.6
    },
    {
      "ticker": "0881.HK",
      "name": "Zhongsheng Group",
      "signal_date": "2021-02-25",
      "entry_date": "2021-02-26",
      "entry_price": 48.0,
      "exit_date": "2021-04-14",
      "exit_price": 53.5,
      "stop_loss": 43.73,
      "target_price": 61.9,
      "exit_reason": "max_hold",
      "holding_days": 47,
      "pnl_pct": 11.46,
      "confidence": 0.92,
      "risk_reward": 3.25
    },
    {
      "ticker": "0175.HK",
      "name": "Geely Auto",
      "signal_date": "2021-03-23",
      "entry_date": "2021-03-24",
      "entry_price": 21.85,
      "exit_date": "2021-03-24",
      "exit_price": 21.17,
      "stop_loss": 21.17,
      "target_price": 33.8,
      "exit_reason": "stop_loss",
      "holding_days": 0,
      "pnl_pct": -3.11,
      "confidence": 0.88,
      "risk_reward": 17.52
    },
    {
      "ticker": "1211.HK",
      "name": "BYD Company",
      "signal_date": "2021-03-23",
      "entry_date": "2021-03-24",
      "entry_price": 59.33,
      "exit_date": "2021-03-24",
      "exit_price": 56.03,
      "stop_loss": 56.03,
      "target_price": 92.8,
      "exit_reason": "stop_loss",
      "holding_days": 0,
      "pnl_pct": -5.56,
      "confidence": 0.88,
      "risk_reward": 10.14
    },
    {
      "ticker": "9618.HK",
      "name": "JD.com",
      "signal_date": "2021-04-12",
      "entry_date": "2021-04-13",
      "entry_price": 305.2,
      "exit_date": "2021-04-13",
      "exit_price": 295.49,
      "stop_loss": 295.49,
      "target_price": 416.8,
      "exit_reason": "stop_loss",
      "holding_days": 0,
      "pnl_pct": -3.18,
      "confidence": 0.88,
      "risk_reward": 11.49
    },
    {
      "ticker": "0968.HK",
      "name": "Xinyi Solar",
      "signal_date": "2021-04-08",
      "entry_date": "2021-04-09",
      "entry_price": 13.4,
      "exit_date": "2021-05-05",
      "exit_price": 12.1,
      "stop_loss": 12.1,
      "target_price": 22.1,
      "exit_reason": "stop_loss",
      "holding_days": 26,
      "pnl_pct": -9.7,
      "confidence": 0.92,
      "risk_reward": 6.67
    },
    {
      "ticker": "6862.HK",
      "name": "Haidilao",
      "signal_date": "2021-05-28",
      "entry_date": "2021-05-31",
      "entry_price": 43.85,
      "exit_date": "2021-06-10",
      "exit_price": 40.37,
      "stop_loss": 40.37,
      "target_price": 83.55,
      "exit_reason": "stop_loss",
      "holding_days": 10,
      "pnl_pct": -7.94,
      "confidence": 0.92,
      "risk_reward": 11.4
    },
    {
      "ticker": "0700.HK",
      "name": "Tencent",
      "signal_date": "2021-05-27",
      "entry_date": "2021-05-28",
      "entry_price": 560.49,
      "exit_date": "2021-07-05",
      "exit_price": 513.29,
      "stop_loss": 513.29,
      "target_price": 706.6,
      "exit_reason": "stop_loss",
      "holding_days": 38,
      "pnl_pct": -8.42,
      "confidence": 0.8,
      "risk_reward": 3.1
    },
    {
      "ticker": "0027.HK",
      "name": "Galaxy Entertainment",
      "signal_date": "2021-06-07",
      "entry_date": "2021-06-08",
      "entry_price": 62.9,
      "exit_date": "2021-06-23",
      "exit_price": 59.62,
      "stop_loss": 59.62,
      "target_price": 78.25,
      "exit_reason": "stop_loss",
      "holding_days": 15,
      "pnl_pct": -5.21,
      "confidence": 0.8,
      "risk_reward": 4.67
    },
    {
      "ticker": "1928.HK",
      "name": "Sands China",
      "signal_date": "2021-06-07",
      "entry_date": "2021-06-08",
      "entry_price": 33.7,
      "exit_date": "2021-07-07",
      "exit_price": 31.82,
      "stop_loss": 31.82,
      "target_price": 40.2,
      "exit_reason": "stop_loss",
      "holding_days": 29,
      "pnl_pct": -5.58,
      "confidence": 0.8,
      "risk_reward": 3.46
    },
    {
      "ticker": "1378.HK",
      "name": "China Hongqiao",
      "signal_date": "2021-07-14",
      "entry_date": "2021-07-15",
      "entry_price": 10.12,
      "exit_date": "2021-07-28",
      "exit_price": 9.51,
      "stop_loss": 9.51,
      "target_price": 14.06,
      "exit_reason": "stop_loss",
      "holding_days": 13,
      "pnl_pct": -6.03,
      "confidence": 0.8,
      "risk_reward": 6.5
    },
    {
      "ticker": "9988.HK",
      "name": "Alibaba",
      "signal_date": "2021-07-23",
      "entry_date": "2021-07-26",
      "entry_price": 199.2,
      "exit_date": "2021-07-27",
      "exit_price": 187.68,
      "stop_loss": 187.68,
      "target_price": 267.0,
      "exit_reason": "stop_loss",
      "holding_days": 1,
      "pnl_pct": -5.78,
      "confidence": 0.8,
      "risk_reward": 5.89
    },
    {
      "ticker": "6862.HK",
      "name": "Haidilao",
      "signal_date": "2021-08-19",
      "entry_date": "2021-08-20",
      "entry_price": 28.5,
      "exit_date": "2021-08-20",
      "exit_price": 26.45,
      "stop_loss": 26.45,
      "target_price": 68.85,
      "exit_reason": "stop_loss",
      "holding_days": 0,
      "pnl_pct": -7.19,
      "confidence": 0.8,
      "risk_reward": 19.66
    },
    {
      "ticker": "2313.HK",
      "name": "Shenzhou International",
      "signal_date": "2021-08-26",
      "entry_date": "2021-08-27",
      "entry_price": 158.9,
      "exit_date": "2021-08-27",
      "exit_price": 155.52,
      "stop_loss": 155.52,
      "target_price": 207.6,
      "exit_reason": "stop_loss",
      "holding_days": 0,
      "pnl_pct": -2.13,
      "confidence": 0.95,
      "risk_reward": 14.41
    },
    {
      "ticker": "0960.HK",
      "name": "Longfor Group",
      "signal_date": "2021-09-14",
      "entry_date": "2021-09-15",
      "entry_price": 34.6,
      "exit_date": "2021-09-16",
      "exit_price": 32.35,
      "stop_loss": 32.35,
      "target_price": 53.45,
      "exit_reason": "stop_loss",
      "holding_days": 1,
      "pnl_pct": -6.5,
      "confidence": 0.88,
      "risk_reward": 8.39
    },
    {
      "ticker": "0288.HK",
      "name": "WH Group",
      "signal_date": "2021-09-08",
      "entry_date": "2021-09-09",
      "entry_price": 5.7,
      "exit_date": "2021-10-04",
      "exit_price": 5.35,
      "stop_loss": 5.35,
      "target_price": 7.36,
      "exit_reason": "stop_loss",
      "holding_days": 25,
      "pnl_pct": -6.14,
      "confidence": 0.8,
      "risk_reward": 4.71
    },
    {
      "ticker": "2020.HK",
      "name": "ANTA Sports",
      "signal_date": "2021-10-28",
      "entry_date": "2021-10-29",
      "entry_price": 121.6,
      "exit_date": "2021-11-01",
      "exit_price": 116.54,
      "stop_loss": 116.54,
      "target_price": 189.7,
      "exit_reason": "stop_loss",
      "holding_days": 3,
      "pnl_pct": -4.16,
      "confidence": 0.95,
      "risk_reward": 13.47
    },
    {
      "ticker": "1177.HK",
      "name": "Sino Biopharmaceutical",
      "signal_date": "2021-10-26",
      "entry_date": "2021-10-27",
      "entry_price": 5.8,
      "exit_date": "2021-11-03",
      "exit_price": 5.51,
      "stop_loss": 5.51,
      "target_price": 9.05,
      "exit_reason": "stop_loss",
      "holding_days": 7,
      "pnl_pct": -5.0,
      "confidence": 0.88,
      "risk_reward": 11.22
    },
    {
      "ticker": "6862.HK",
      "name": "Haidilao",
      "signal_date": "2021-11-17",
      "entry_date": "2021-11-18",
      "entry_price": 20.5,
      "exit_date": "2021-11-22",
      "exit_price": 19.16,
      "stop_loss": 19.16,
      "target_price": 48.05,
      "exit_reason": "stop_loss",
      "holding_days": 4,
      "pnl_pct": -6.54,
      "confidence": 0.92,
      "risk_reward": 20.58
    },
    {
      "ticker": "1378.HK",
      "name": "China Hongqiao",
      "signal_date": "2021-11-22",
      "entry_date": "2021-11-23",
      "entry_price": 7.54,
      "exit_date": "2022-01-05",
      "exit_price": 8.28,
      "stop_loss": 6.89,
      "target_price": 13.88,
      "exit_reason": "max_hold",
      "holding_days": 43,
      "pnl_pct": 9.81,
      "confidence": 0.88,
      "risk_reward": 9.8
    },
    {
      "ticker": "0968.HK",
      "name": "Xinyi Solar",
      "signal_date": "2021-12-17",
      "entry_date": "2021-12-20",
      "entry_price": 13.62,
      "exit_date": "2021-12-20",
      "exit_price": 12.96,
      "stop_loss": 12.96,
      "target_price": 18.88,
      "exit_reason": "stop_loss",
      "holding_days": 0,
      "pnl_pct": -4.85,
      "confidence": 0.92,
      "risk_reward": 7.97
    },
    {
      "ticker": "1093.HK",
      "name": "CSPC Pharmaceutical",
      "signal_date": "2021-12-06",
      "entry_date": "2021-12-07",
      "entry_price": 8.09,
      "exit_date": "2022-01-19",
      "exit_price": 9.72,
      "stop_loss": 7.57,
      "target_price": 11.24,
      "exit_reason": "max_hold",
      "holding_days": 43,
      "pnl_pct": 20.15,
      "confidence": 0.95,
      "risk_reward": 6.11
    },
    {
      "ticker": "0241.HK",
      "name": "Ali Health",
      "signal_date": "2022-01-27",
      "entry_date": "2022-01-28",
      "entry_price": 6.06,
      "exit_date": "2022-02-22",
      "exit_price": 5.54,
      "stop_loss": 5.54,
      "target_price": 13.32,
      "exit_reason": "stop_loss",
      "holding_days": 25,
      "pnl_pct": -8.58,
      "confidence": 0.8,
      "risk_reward": 13.94
    },
    {
      "ticker": "2020.HK",
      "name": "ANTA Sports",
      "signal_date": "2022-01-06",
      "entry_date": "2022-01-07",
      "entry_price": 111.4,
      "exit_date": "2022-02-23",
      "exit_price": 122.0,
      "stop_loss": 105.22,
      "target_price": 186.5,
      "exit_reason": "max_hold",
      "holding_days": 47,
      "pnl_pct": 9.52,
      "confidence": 0.88,
      "risk_reward": 12.14
    },
    {
      "ticker": "6862.HK",
      "name": "Haidilao",
      "signal_date": "2022-02-07",
      "entry_date": "2022-02-08",
      "entry_price": 18.08,
      "exit_date": "2022-03-07",
      "exit_price": 15.69,
      "stop_loss": 15.69,
      "target_price": 33.7,
      "exit_reason": "stop_loss",
      "holding_days": 27,
      "pnl_pct": -13.22,
      "confidence": 0.7,
      "risk_reward": 6.53
    },
    {
      "ticker": "6618.HK",
      "name": "JD Health",
      "signal_date": "2022-02-11",
      "entry_date": "2022-02-14",
      "entry_price": 60.4,
      "exit_date": "2022-03-07",
      "exit_price": 51.79,
      "stop_loss": 51.79,
      "target_price": 79.25,
      "exit_reason": "stop_loss",
      "holding_days": 21,
      "pnl_pct": -14.25,
      "confidence": 0.82,
      "risk_reward": 2.19
    },
    {
      "ticker": "0175.HK",
      "name": "Geely Auto",
      "signal_date": "2022-03-28",
      "entry_date": "2022-03-29",
      "entry_price": 11.78,
      "exit_date": "2022-05-17",
      "exit_price": 13.64,
      "stop_loss": 9.89,
      "target_price": 27.1,
      "exit_reason": "max_hold",
      "holding_days": 49,
      "pnl_pct": 15.79,
      "confidence": 0.92,
      "risk_reward": 8.1
    },
    {
      "ticker": "0291.HK",
      "name": "China Resources Beer",
      "signal_date": "2022-03-28",
      "entry_date": "2022-03-29",
      "entry_price": 45.85,
      "exit_date": "2022-04-11",
      "exit_price": 41.38,
      "stop_loss": 41.38,
      "target_price": 67.45,
      "exit_reason": "stop_loss",
      "holding_days": 13,
      "pnl_pct": -9.75,
      "confidence": 0.95,
      "risk_reward": 4.83
    },
    {
      "ticker": "2331.HK",
      "name": "Li Ning",
      "signal_date": "2022-04-11",
      "entry_date": "2022-04-12",
      "entry_price": 56.85,
      "exit_date": "2022-05-26",
      "exit_price": 48.91,
      "stop_loss": 48.91,
      "target_price": 96.1,
      "exit_reason": "stop_loss",
      "holding_days": 44,
      "pnl_pct": -13.97,
      "confidence": 0.92,
      "risk_reward": 4.94
    },
    {
      "ticker": "3968.HK",
      "name": "China Merchants Bank",
      "signal_date": "2022-04-14",
      "entry_date": "2022-04-19",
      "entry_price": 53.7,
      "exit_date": "2022-04-21",
      "exit_price": 50.06,
      "stop_loss": 50.06,
      "target_price": 70.72,
      "exit_reason": "stop_loss",
      "holding_days": 2,
      "pnl_pct": -6.78,
      "confidence": 0.8,
      "risk_reward": 4.68
    },
    {
      "ticker": "6098.HK",
      "name": "CG Services",
      "signal_date": "2022-05-26",
      "entry_date": "2022-05-27",
      "entry_price": 28.1,
      "exit_date": "2022-07-12",
      "exit_price": 27.15,
      "stop_loss": 24.43,
      "target_price": 54.35,
      "exit_reason": "max_hold",
      "holding_days": 46,
      "pnl_pct": -3.38,
      "confidence": 0.88,
      "risk_reward": 7.16
    },
    {
      "ticker": "2319.HK",
      "name": "China Mengniu",
      "signal_date": "2022-05-25",
      "entry_date": "2022-05-26",
      "entry_price": 39.05,
      "exit_date": "2022-06-13",
      "exit_price": 36.77,
      "stop_loss": 36.77,
      "target_price": 50.8,
      "exit_reason": "stop_loss",
      "holding_days": 18,
      "pnl_pct": -5.84,
      "confidence": 0.88,
      "risk_reward": 5.15
    },
    {
      "ticker": "2018.HK",
      "name": "AAC Technologies",
      "signal_date": "2022-06-14",
      "entry_date": "2022-06-15",
      "entry_price": 16.86,
      "exit_date": "2022-07-28",
      "exit_price": 15.96,
      "stop_loss": 14.76,
      "target_price": 33.75,
      "exit_reason": "max_hold",
      "holding_days": 43,
      "pnl_pct": -5.34,
      "confidence": 0.92,
      "risk_reward": 8.06
    },
    {
      "ticker": "2020.HK",
      "name": "ANTA Sports",
      "signal_date": "2022-06-16",
      "entry_date": "2022-06-17",
      "entry_price": 83.0,
      "exit_date": "2022-08-01",
      "exit_price": 86.85,
      "stop_loss": 74.98,
      "target_price": 129.9,
      "exit_reason": "max_hold",
      "holding_days": 45,
      "pnl_pct": 4.64,
      "confidence": 0.8,
      "risk_reward": 5.84
    },
    {
      "ticker": "2313.HK",
      "name": "Shenzhou International",
      "signal_date": "2022-07-05",
      "entry_date": "2022-07-06",
      "entry_price": 91.0,
      "exit_date": "2022-07-08",
      "exit_price": 86.69,
      "stop_loss": 86.69,
      "target_price": 158.2,
      "exit_reason": "stop_loss",
      "holding_days": 2,
      "pnl_pct": -4.74,
      "confidence": 0.95,
      "risk_reward": 15.58
    },
    {
      "ticker": "3968.HK",
      "name": "China Merchants Bank",
      "signal_date": "2022-07-28",
      "entry_date": "2022-07-29",
      "entry_price": 43.25,
      "exit_date": "2022-08-10",
      "exit_price": 39.7,
      "stop_loss": 39.7,
      "target_price": 70.2,
      "exit_reason": "stop_loss",
      "holding_days": 12,
      "pnl_pct": -8.21,
      "confidence": 0.88,
      "risk_reward": 7.58
    },
    {
      "ticker": "2007.HK",
      "name": "Country Garden",
      "signal_date": "2022-08-30",
      "entry_date": "2022-08-31",
      "entry_price": 2.45,
      "exit_date": "2022-09-02",
      "exit_price": 2.23,
      "stop_loss": 2.23,
      "target_price": 6.63,
      "exit_reason": "stop_loss",
      "holding_days": 2,
      "pnl_pct": -8.98,
      "confidence": 0.8,
      "risk_reward": 18.76
    },
    {
      "ticker": "6098.HK",
      "name": "CG Services",
      "signal_date": "2022-08-30",
      "entry_date": "2022-08-31",
      "entry_price": 15.1,
      "exit_date": "2022-09-28",
      "exit_price": 13.29,
      "stop_loss": 13.29,
      "target_price": 44.7,
      "exit_reason": "stop_loss",
      "holding_days": 28,
      "pnl_pct": -11.99,
      "confidence": 0.8,
      "risk_reward": 16.32
    },
    {
      "ticker": "2319.HK",
      "name": "China Mengniu",
      "signal_date": "2022-09-06",
      "entry_date": "2022-09-07",
      "entry_price": 31.7,
      "exit_date": "2022-09-29",
      "exit_price": 30.91,
      "stop_loss": 30.91,
      "target_price": 46.55,
      "exit_reason": "stop_loss",
      "holding_days": 22,
      "pnl_pct": -2.49,
      "confidence": 0.8,
      "risk_reward": 18.85
    },
    {
      "ticker": "2018.HK",
      "name": "AAC Technologies",
      "signal_date": "2022-09-06",
      "entry_date": "2022-09-07",
      "entry_price": 14.06,
      "exit_date": "2022-09-19",
      "exit_price": 13.29,
      "stop_loss": 13.29,
      "target_price": 18.92,
      "exit_reason": "stop_loss",
      "holding_days": 12,
      "pnl_pct": -5.48,
      "confidence": 0.92,
      "risk_reward": 6.28
    },
    {
      "ticker": "0881.HK",
      "name": "Zhongsheng Group",
      "signal_date": "2022-10-28",
      "entry_date": "2022-10-31",
      "entry_price": 30.55,
      "exit_date": "2022-10-31",
      "exit_price": 29.76,
      "stop_loss": 29.76,
      "target_price": 60.5,
      "exit_reason": "stop_loss",
      "holding_days": 0,
      "pnl_pct": -2.59,
      "confidence": 0.92,
      "risk_reward": 37.91
    },
    {
      "ticker": "9961.HK",
      "name": "Trip.com",
      "signal_date": "2022-10-11",
      "entry_date": "2022-10-12",
      "entry_price": 190.3,
      "exit_date": "2022-10-12",
      "exit_price": 186.43,
      "stop_loss": 186.43,
      "target_price": 233.68,
      "exit_reason": "stop_loss",
      "holding_days": 0,
      "pnl_pct": -2.03,
      "confidence": 0.92,
      "risk_reward": 11.22
    },
    {
      "ticker": "0669.HK",
      "name": "Techtronic Ind",
      "signal_date": "2022-11-03",
      "entry_date": "2022-11-04",
      "entry_price": 75.2,
      "exit_date": "2022-12-16",
      "exit_price": 90.95,
      "stop_loss": 71.38,
      "target_price": 106.6,
      "exit_reason": "max_hold",
      "holding_days": 42,
      "pnl_pct": 20.94,
      "confidence": 0.8,
      "risk_reward": 8.21
    },
    {
      "ticker": "3690.HK",
      "name": "Meituan",
      "signal_date": "2022-11-25",
      "entry_date": "2022-11-28",
      "entry_price": 129.0,
      "exit_date": "2023-01-12",
      "exit_price": 173.0,
      "stop_loss": 115.78,
      "target_price": 208.2,
      "exit_reason": "max_hold",
      "holding_days": 45,
      "pnl_pct": 34.11,
      "confidence": 0.92,
      "risk_reward": 5.99
    },
    {
      "ticker": "1211.HK",
      "name": "BYD Company",
      "signal_date": "2022-12-01",
      "entry_date": "2022-12-02",
      "entry_price": 63.67,
      "exit_date": "2023-01-18",
      "exit_price": 73.87,
      "stop_loss": 53.02,
      "target_price": 98.6,
      "exit_reason": "max_hold",
      "holding_days": 47,
      "pnl_pct": 16.01,
      "confidence": 0.92,
      "risk_reward": 3.28
    },
    {
      "ticker": "6098.HK",
      "name": "CG Services",
      "signal_date": "2022-12-01",
      "entry_date": "2022-12-02",
      "entry_price": 19.68,
      "exit_date": "2023-01-18",
      "exit_price": 19.04,
      "stop_loss": 6.59,
      "target_price": 35.35,
      "exit_reason": "max_hold",
      "holding_days": 47,
      "pnl_pct": -3.25,
      "confidence": 0.77,
      "risk_reward": 1.2
    },
    {
      "ticker": "1876.HK",
      "name": "Budweiser APAC",
      "signal_date": "2023-03-07",
      "entry_date": "2023-03-08",
      "entry_price": 23.25,
      "exit_date": "2023-04-24",
      "exit_price": 23.2,
      "stop_loss": 21.98,
      "target_price": 27.0,
      "exit_reason": "max_hold",
      "holding_days": 47,
      "pnl_pct": -0.22,
      "confidence": 0.82,
      "risk_reward": 2.96
    },
    {
      "ticker": "0017.HK",
      "name": "New World Dev",
      "signal_date": "2023-03-14",
      "entry_date": "2023-03-15",
      "entry_price": 21.5,
      "exit_date": "2023-04-25",
      "exit_price": 19.87,
      "stop_loss": 19.87,
      "target_price": 24.6,
      "exit_reason": "stop_loss",
      "holding_days": 41,
      "pnl_pct": -7.58,
      "confidence": 0.77,
      "risk_reward": 1.9
    },
    {
      "ticker": "3968.HK",
      "name": "China Merchants Bank",
      "signal_date": "2023-04-26",
      "entry_date": "2023-04-27",
      "entry_price": 38.4,
      "exit_date": "2023-04-27",
      "exit_price": 37.58,
      "stop_loss": 37.58,
      "target_price": 52.95,
      "exit_reason": "stop_loss",
      "holding_days": 0,
      "pnl_pct": -2.14,
      "confidence": 0.8,
      "risk_reward": 17.83
    },
    {
      "ticker": "2269.HK",
      "name": "WuXi Biologics",
      "signal_date": "2023-04-04",
      "entry_date": "2023-04-06",
      "entry_price": 45.85,
      "exit_date": "2023-05-18",
      "exit_price": 43.34,
      "stop_loss": 43.34,
      "target_price": 73.9,
      "exit_reason": "stop_loss",
      "holding_days": 42,
      "pnl_pct": -5.47,
      "confidence": 0.88,
      "risk_reward": 11.19
    },
    {
      "ticker": "2018.HK",
      "name": "AAC Technologies",
      "signal_date": "2023-05-02",
      "entry_date": "2023-05-03",
      "entry_price": 16.54,
      "exit_date": "2023-06-01",
      "exit_price": 15.24,
      "stop_loss": 15.24,
      "target_price": 22.3,
      "exit_reason": "stop_loss",
      "holding_days": 29,
      "pnl_pct": -7.86,
      "confidence": 0.88,
      "risk_reward": 4.45
    },
    {
      "ticker": "1378.HK",
      "name": "China Hongqiao",
      "signal_date": "2023-05-11",
      "entry_date": "2023-05-12",
      "entry_price": 7.36,
      "exit_date": "2023-05-12",
      "exit_price": 6.95,
      "stop_loss": 6.95,
      "target_price": 9.3,
      "exit_reason": "stop_loss",
      "holding_days": 0,
      "pnl_pct": -5.57,
      "confidence": 0.78,
      "risk_reward": 4.74
    },
    {
      "ticker": "0868.HK",
      "name": "Xinyi Glass",
      "signal_date": "2023-06-23",
      "entry_date": "2023-06-26",
      "entry_price": 11.32,
      "exit_date": "2023-08-08",
      "exit_price": 12.06,
      "stop_loss": 11.0,
      "target_price": 17.66,
      "exit_reason": "max_hold",
      "holding_days": 43,
      "pnl_pct": 6.54,
      "confidence": 0.88,
      "risk_reward": 19.91
    },
    {
      "ticker": "0241.HK",
      "name": "Ali Health",
      "signal_date": "2023-06-21",
      "entry_date": "2023-06-23",
      "entry_price": 4.6,
      "exit_date": "2023-06-26",
      "exit_price": 4.44,
      "stop_loss": 4.44,
      "target_price": 7.68,
      "exit_reason": "stop_loss",
      "holding_days": 3,
      "pnl_pct": -3.48,
      "confidence": 0.8,
      "risk_reward": 19.85
    },
    {
      "ticker": "2688.HK",
      "name": "ENN Energy",
      "signal_date": "2023-07-21",
      "entry_date": "2023-07-24",
      "entry_price": 84.5,
      "exit_date": "2023-08-21",
      "exit_price": 81.41,
      "stop_loss": 81.41,
      "target_price": 126.0,
      "exit_reason": "stop_loss",
      "holding_days": 28,
      "pnl_pct": -3.66,
      "confidence": 0.88,
      "risk_reward": 13.42
    },
    {
      "ticker": "1177.HK",
      "name": "Sino Biopharmaceutical",
      "signal_date": "2023-07-06",
      "entry_date": "2023-07-07",
      "entry_price": 3.44,
      "exit_date": "2023-08-07",
      "exit_price": 3.2,
      "stop_loss": 3.2,
      "target_price": 4.99,
      "exit_reason": "stop_loss",
      "holding_days": 31,
      "pnl_pct": -6.98,
      "confidence": 0.95,
      "risk_reward": 6.37
    },
    {
      "ticker": "0291.HK",
      "name": "China Resources Beer",
      "signal_date": "2023-09-07",
      "entry_date": "2023-09-11",
      "entry_price": 44.3,
      "exit_date": "2023-09-20",
      "exit_price": 42.86,
      "stop_loss": 42.86,
      "target_price": 64.75,
      "exit_reason": "stop_loss",
      "holding_days": 9,
      "pnl_pct": -3.25,
      "confidence": 0.8,
      "risk_reward": 14.24
    },
    {
      "ticker": "1093.HK",
      "name": "CSPC Pharmaceutical",
      "signal_date": "2023-09-06",
      "entry_date": "2023-09-07",
      "entry_price": 5.68,
      "exit_date": "2023-10-03",
      "exit_price": 5.4,
      "stop_loss": 5.4,
      "target_price": 8.35,
      "exit_reason": "stop_loss",
      "holding_days": 26,
      "pnl_pct": -4.93,
      "confidence": 0.92,
      "risk_reward": 9.38
    },
    {
      "ticker": "0322.HK",
      "name": "TCL Electronics",
      "signal_date": "2023-10-13",
      "entry_date": "2023-10-16",
      "entry_price": 10.44,
      "exit_date": "2023-10-16",
      "exit_price": 10.08,
      "stop_loss": 10.08,
      "target_price": 13.88,
      "exit_reason": "stop_loss",
      "holding_days": 0,
      "pnl_pct": -3.45,
      "confidence": 0.8,
      "risk_reward": 9.56
    },
    {
      "ticker": "6618.HK",
      "name": "JD Health",
      "signal_date": "2023-10-12",
      "entry_date": "2023-10-13",
      "entry_price": 39.0,
      "exit_date": "2023-10-19",
      "exit_price": 36.14,
      "stop_loss": 36.14,
      "target_price": 57.1,
      "exit_reason": "stop_loss",
      "holding_days": 6,
      "pnl_pct": -7.33,
      "confidence": 0.8,
      "risk_reward": 6.34
    },
    {
      "ticker": "2331.HK",
      "name": "Li Ning",
      "signal_date": "2023-11-09",
      "entry_date": "2023-11-10",
      "entry_price": 24.65,
      "exit_date": "2023-11-17",
      "exit_price": 22.99,
      "stop_loss": 22.99,
      "target_price": 49.85,
      "exit_reason": "stop_loss",
      "holding_days": 7,
      "pnl_pct": -6.73,
      "confidence": 0.95,
      "risk_reward": 15.2
    },
    {
      "ticker": "2007.HK",
      "name": "Country Garden",
      "signal_date": "2023-11-10",
      "entry_date": "2023-11-13",
      "entry_price": 0.77,
      "exit_date": "2023-12-27",
      "exit_price": 0.72,
      "stop_loss": 0.65,
      "target_price": 1.87,
      "exit_reason": "max_hold",
      "holding_days": 44,
      "pnl_pct": -6.49,
      "confidence": 0.92,
      "risk_reward": 9.39
    },
    {
      "ticker": "0968.HK",
      "name": "Xinyi Solar",
      "signal_date": "2023-12-28",
      "entry_date": "2023-12-29",
      "entry_price": 4.59,
      "exit_date": "2024-01-17",
      "exit_price": 3.82,
      "stop_loss": 3.82,
      "target_price": 9.13,
      "exit_reason": "stop_loss",
      "holding_days": 19,
      "pnl_pct": -16.78,
      "confidence": 0.8,
      "risk_reward": 5.9
    },
    {
      "ticker": "2688.HK",
      "name": "ENN Energy",
      "signal_date": "2023-12-28",
      "entry_date": "2023-12-29",
      "entry_price": 57.0,
      "exit_date": "2024-02-14",
      "exit_price": 53.9,
      "stop_loss": 47.71,
      "target_price": 96.3,
      "exit_reason": "max_hold",
      "holding_days": 47,
      "pnl_pct": -5.44,
      "confidence": 0.8,
      "risk_reward": 4.23
    },
    {
      "ticker": "1997.HK",
      "name": "Wharf REIC",
      "signal_date": "2024-01-04",
      "entry_date": "2024-01-05",
      "entry_price": 24.05,
      "exit_date": "2024-01-22",
      "exit_price": 22.51,
      "stop_loss": 22.51,
      "target_price": 41.8,
      "exit_reason": "stop_loss",
      "holding_days": 17,
      "pnl_pct": -6.4,
      "confidence": 0.92,
      "risk_reward": 11.54
    },
    {
      "ticker": "0388.HK",
      "name": "HKEX",
      "signal_date": "2024-01-09",
      "entry_date": "2024-01-10",
      "entry_price": 245.8,
      "exit_date": "2024-01-17",
      "exit_price": 235.39,
      "stop_loss": 235.39,
      "target_price": 325.8,
      "exit_reason": "stop_loss",
      "holding_days": 7,
      "pnl_pct": -4.24,
      "confidence": 0.88,
      "risk_reward": 7.69
    },
    {
      "ticker": "2269.HK",
      "name": "WuXi Biologics",
      "signal_date": "2024-02-28",
      "entry_date": "2024-02-29",
      "entry_price": 18.22,
      "exit_date": "2024-03-15",
      "exit_price": 14.8,
      "stop_loss": 14.8,
      "target_price": 51.0,
      "exit_reason": "stop_loss",
      "holding_days": 15,
      "pnl_pct": -18.77,
      "confidence": 0.8,
      "risk_reward": 9.59
    },
    {
      "ticker": "0017.HK",
      "name": "New World Dev",
      "signal_date": "2024-02-28",
      "entry_date": "2024-02-29",
      "entry_price": 10.0,
      "exit_date": "2024-03-04",
      "exit_price": 8.89,
      "stop_loss": 8.89,
      "target_price": 17.4,
      "exit_reason": "stop_loss",
      "holding_days": 4,
      "pnl_pct": -11.1,
      "confidence": 0.92,
      "risk_reward": 6.66
    },
    {
      "ticker": "0881.HK",
      "name": "Zhongsheng Group",
      "signal_date": "2024-03-05",
      "entry_date": "2024-03-06",
      "entry_price": 13.18,
      "exit_date": "2024-03-26",
      "exit_price": 12.61,
      "stop_loss": 12.61,
      "target_price": 22.95,
      "exit_reason": "stop_loss",
      "holding_days": 20,
      "pnl_pct": -4.32,
      "confidence": 0.92,
      "risk_reward": 17.27
    },
    {
      "ticker": "0066.HK",
      "name": "MTR Corporation",
      "signal_date": "2024-03-04",
      "entry_date": "2024-03-05",
      "entry_price": 25.15,
      "exit_date": "2024-04-17",
      "exit_price": 23.9,
      "stop_loss": 23.9,
      "target_price": 32.05,
      "exit_reason": "stop_loss",
      "holding_days": 43,
      "pnl_pct": -4.97,
      "confidence": 0.92,
      "risk_reward": 5.54
    },
    {
      "ticker": "0101.HK",
      "name": "Hang Lung Properties",
      "signal_date": "2024-04-25",
      "entry_date": "2024-04-26",
      "entry_price": 8.35,
      "exit_date": "2024-05-24",
      "exit_price": 7.67,
      "stop_loss": 7.67,
      "target_price": 11.42,
      "exit_reason": "stop_loss",
      "holding_days": 28,
      "pnl_pct": -8.14,
      "confidence": 0.92,
      "risk_reward": 4.52
    },
    {
      "ticker": "1929.HK",
      "name": "Chow Tai Fook",
      "signal_date": "2024-04-29",
      "entry_date": "2024-04-30",
      "entry_price": 11.02,
      "exit_date": "2024-06-06",
      "exit_price": 9.77,
      "stop_loss": 9.77,
      "target_price": 12.82,
      "exit_reason": "stop_loss",
      "holding_days": 37,
      "pnl_pct": -11.34,
      "confidence": 0.73,
      "risk_reward": 1.44
    },
    {
      "ticker": "9999.HK",
      "name": "NetEase",
      "signal_date": "2024-05-24",
      "entry_date": "2024-05-27",
      "entry_price": 142.4,
      "exit_date": "2024-07-10",
      "exit_price": 141.7,
      "stop_loss": 135.46,
      "target_price": 176.7,
      "exit_reason": "max_hold",
      "holding_days": 44,
      "pnl_pct": -0.49,
      "confidence": 0.9,
      "risk_reward": 4.94
    },
    {
      "ticker": "0017.HK",
      "name": "New World Dev",
      "signal_date": "2024-05-08",
      "entry_date": "2024-05-09",
      "entry_price": 8.68,
      "exit_date": "2024-06-24",
      "exit_price": 7.26,
      "stop_loss": 7.11,
      "target_price": 15.82,
      "exit_reason": "max_hold",
      "holding_days": 46,
      "pnl_pct": -16.36,
      "confidence": 0.8,
      "risk_reward": 4.56
    },
    {
      "ticker": "0960.HK",
      "name": "Longfor Group",
      "signal_date": "2024-06-03",
      "entry_date": "2024-06-04",
      "entry_price": 12.46,
      "exit_date": "2024-07-18",
      "exit_price": 11.36,
      "stop_loss": 8.74,
      "target_price": 17.41,
      "exit_reason": "max_hold",
      "holding_days": 44,
      "pnl_pct": -8.83,
      "confidence": 0.55,
      "risk_reward": 1.33
    },
    {
      "ticker": "1024.HK",
      "name": "Kuaishou Tech",
      "signal_date": "2024-07-19",
      "entry_date": "2024-07-22",
      "entry_price": 44.55,
      "exit_date": "2024-07-25",
      "exit_price": 42.96,
      "stop_loss": 42.96,
      "target_price": 62.2,
      "exit_reason": "stop_loss",
      "holding_days": 3,
      "pnl_pct": -3.57,
      "confidence": 0.8,
      "risk_reward": 11.1
    },
    {
      "ticker": "0968.HK",
      "name": "Xinyi Solar",
      "signal_date": "2024-07-19",
      "entry_date": "2024-07-22",
      "entry_price": 3.7,
      "exit_date": "2024-08-13",
      "exit_price": 3.32,
      "stop_loss": 3.32,
      "target_price": 6.68,
      "exit_reason": "stop_loss",
      "holding_days": 22,
      "pnl_pct": -10.27,
      "confidence": 0.88,
      "risk_reward": 7.88
    },
    {
      "ticker": "2319.HK",
      "name": "China Mengniu",
      "signal_date": "2024-08-15",
      "entry_date": "2024-08-16",
      "entry_price": 12.9,
      "exit_date": "2024-08-22",
      "exit_price": 12.06,
      "stop_loss": 12.06,
      "target_price": 21.0,
      "exit_reason": "stop_loss",
      "holding_days": 6,
      "pnl_pct": -6.51,
      "confidence": 0.88,
      "risk_reward": 9.62
    },
    {
      "ticker": "2313.HK",
      "name": "Shenzhou International",
      "signal_date": "2024-08-28",
      "entry_date": "2024-08-29",
      "entry_price": 61.8,
      "exit_date": "2024-08-29",
      "exit_price": 58.8,
      "stop_loss": 58.8,
      "target_price": 86.2,
      "exit_reason": "stop_loss",
      "holding_days": 0,
      "pnl_pct": -4.85,
      "confidence": 0.92,
      "risk_reward": 8.13
    },
    {
      "ticker": "1928.HK",
      "name": "Sands China",
      "signal_date": "2024-09-02",
      "entry_date": "2024-09-03",
      "entry_price": 13.92,
      "exit_date": "2024-10-21",
      "exit_price": 18.12,
      "stop_loss": 13.02,
      "target_price": 23.0,
      "exit_reason": "max_hold",
      "holding_days": 48,
      "pnl_pct": 30.17,
      "confidence": 0.92,
      "risk_reward": 10.06
    },
    {
      "ticker": "0881.HK",
      "name": "Zhongsheng Group",
      "signal_date": "2024-09-23",
      "entry_date": "2024-09-24",
      "entry_price": 9.17,
      "exit_date": "2024-10-02",
      "exit_price": 16.06,
      "stop_loss": 8.19,
      "target_price": 16.06,
      "exit_reason": "target",
      "holding_days": 8,
      "pnl_pct": 75.14,
      "confidence": 0.92,
      "risk_reward": 7.02
    },
    {
      "ticker": "0968.HK",
      "name": "Xinyi Solar",
      "signal_date": "2024-10-15",
      "entry_date": "2024-10-16",
      "entry_price": 3.09,
      "exit_date": "2024-11-27",
      "exit_price": 3.27,
      "stop_loss": 2.68,
      "target_price": 5.86,
      "exit_reason": "max_hold",
      "holding_days": 42,
      "pnl_pct": 5.83,
      "confidence": 0.92,
      "risk_reward": 6.73
    },
    {
      "ticker": "0857.HK",
      "name": "PetroChina",
      "signal_date": "2024-10-17",
      "entry_date": "2024-10-18",
      "entry_price": 6.06,
      "exit_date": "2024-11-29",
      "exit_price": 5.51,
      "stop_loss": 5.38,
      "target_price": 8.54,
      "exit_reason": "max_hold",
      "holding_days": 42,
      "pnl_pct": -9.08,
      "confidence": 0.92,
      "risk_reward": 3.63
    },
    {
      "ticker": "9999.HK",
      "name": "NetEase",
      "signal_date": "2024-11-21",
      "entry_date": "2024-11-22",
      "entry_price": 137.3,
      "exit_date": "2025-01-08",
      "exit_price": 141.6,
      "stop_loss": 114.62,
      "target_price": 161.1,
      "exit_reason": "max_hold",
      "holding_days": 47,
      "pnl_pct": 3.13,
      "confidence": 0.77,
      "risk_reward": 1.05
    },
    {
      "ticker": "2020.HK",
      "name": "ANTA Sports",
      "signal_date": "2024-12-18",
      "entry_date": "2024-12-19",
      "entry_price": 78.8,
      "exit_date": "2025-02-07",
      "exit_price": 86.0,
      "stop_loss": 72.53,
      "target_price": 106.3,
      "exit_reason": "max_hold",
      "holding_days": 50,
      "pnl_pct": 9.14,
      "confidence": 0.8,
      "risk_reward": 4.38
    },
    {
      "ticker": "6862.HK",
      "name": "Haidilao",
      "signal_date": "2024-12-30",
      "entry_date": "2024-12-31",
      "entry_price": 15.9,
      "exit_date": "2025-01-10",
      "exit_price": 14.11,
      "stop_loss": 14.11,
      "target_price": 19.3,
      "exit_reason": "stop_loss",
      "holding_days": 10,
      "pnl_pct": -11.26,
      "confidence": 0.65,
      "risk_reward": 1.9
    },
    {
      "ticker": "0960.HK",
      "name": "Longfor Group",
      "signal_date": "2025-01-23",
      "entry_date": "2025-01-24",
      "entry_price": 9.63,
      "exit_date": "2025-03-12",
      "exit_price": 10.68,
      "stop_loss": 8.93,
      "target_price": 14.56,
      "exit_reason": "max_hold",
      "holding_days": 47,
      "pnl_pct": 10.9,
      "confidence": 0.8,
      "risk_reward": 7.02
    },
    {
      "ticker": "1997.HK",
      "name": "Wharf REIC",
      "signal_date": "2025-01-24",
      "entry_date": "2025-01-27",
      "entry_price": 19.26,
      "exit_date": "2025-03-13",
      "exit_price": 19.76,
      "stop_loss": 17.78,
      "target_price": 29.0,
      "exit_reason": "max_hold",
      "holding_days": 45,
      "pnl_pct": 2.6,
      "confidence": 0.8,
      "risk_reward": 6.58
    },
    {
      "ticker": "1299.HK",
      "name": "AIA Group",
      "signal_date": "2025-02-05",
      "entry_date": "2025-02-06",
      "entry_price": 52.0,
      "exit_date": "2025-03-20",
      "exit_price": 62.25,
      "stop_loss": 50.06,
      "target_price": 74.55,
      "exit_reason": "max_hold",
      "holding_days": 42,
      "pnl_pct": 19.71,
      "confidence": 0.8,
      "risk_reward": 11.65
    },
    {
      "ticker": "0881.HK",
      "name": "Zhongsheng Group",
      "signal_date": "2025-02-18",
      "entry_date": "2025-02-19",
      "entry_price": 12.52,
      "exit_date": "2025-04-02",
      "exit_price": 14.06,
      "stop_loss": 11.21,
      "target_price": 17.68,
      "exit_reason": "max_hold",
      "holding_days": 42,
      "pnl_pct": 12.3,
      "confidence": 0.92,
      "risk_reward": 3.95
    },
    {
      "ticker": "2313.HK",
      "name": "Shenzhou International",
      "signal_date": "2025-03-03",
      "entry_date": "2025-03-04",
      "entry_price": 56.35,
      "exit_date": "2025-03-07",
      "exit_price": 62.5,
      "stop_loss": 54.53,
      "target_price": 62.5,
      "exit_reason": "target",
      "holding_days": 3,
      "pnl_pct": 10.91,
      "confidence": 0.92,
      "risk_reward": 3.38
    },
    {
      "ticker": "1177.HK",
      "name": "Sino Biopharmaceutical",
      "signal_date": "2025-03-04",
      "entry_date": "2025-03-05",
      "entry_price": 3.27,
      "exit_date": "2025-04-17",
      "exit_price": 3.67,
      "stop_loss": 2.7,
      "target_price": 4.15,
      "exit_reason": "max_hold",
      "holding_days": 43,
      "pnl_pct": 12.23,
      "confidence": 0.77,
      "risk_reward": 1.54
    },
    {
      "ticker": "0968.HK",
      "name": "Xinyi Solar",
      "signal_date": "2025-04-24",
      "entry_date": "2025-04-25",
      "entry_price": 2.59,
      "exit_date": "2025-06-02",
      "exit_price": 2.27,
      "stop_loss": 2.27,
      "target_price": 4.0,
      "exit_reason": "stop_loss",
      "holding_days": 38,
      "pnl_pct": -12.36,
      "confidence": 0.88,
      "risk_reward": 4.35
    },
    {
      "ticker": "2331.HK",
      "name": "Li Ning",
      "signal_date": "2025-04-29",
      "entry_date": "2025-04-30",
      "entry_price": 14.5,
      "exit_date": "2025-06-13",
      "exit_price": 15.48,
      "stop_loss": 13.4,
      "target_price": 19.16,
      "exit_reason": "max_hold",
      "holding_days": 44,
      "pnl_pct": 6.76,
      "confidence": 0.8,
      "risk_reward": 4.24
    },
    {
      "ticker": "0881.HK",
      "name": "Zhongsheng Group",
      "signal_date": "2025-05-02",
      "entry_date": "2025-05-06",
      "entry_price": 11.76,
      "exit_date": "2025-06-17",
      "exit_price": 12.68,
      "stop_loss": 10.62,
      "target_price": 18.94,
      "exit_reason": "max_hold",
      "holding_days": 42,
      "pnl_pct": 7.82,
      "confidence": 0.8,
      "risk_reward": 6.29
    },
    {
      "ticker": "2007.HK",
      "name": "Country Garden",
      "signal_date": "2025-05-16",
      "entry_date": "2025-05-19",
      "entry_price": 0.4,
      "exit_date": "2025-06-30",
      "exit_price": 0.38,
      "stop_loss": 0.36,
      "target_price": 0.57,
      "exit_reason": "max_hold",
      "holding_days": 42,
      "pnl_pct": -5.0,
      "confidence": 0.88,
      "risk_reward": 4.83
    },
    {
      "ticker": "6862.HK",
      "name": "Haidilao",
      "signal_date": "2025-06-12",
      "entry_date": "2025-06-13",
      "entry_price": 14.88,
      "exit_date": "2025-07-14",
      "exit_price": 14.19,
      "stop_loss": 14.19,
      "target_price": 18.68,
      "exit_reason": "stop_loss",
      "holding_days": 31,
      "pnl_pct": -4.64,
      "confidence": 0.8,
      "risk_reward": 5.5
    },
    {
      "ticker": "9618.HK",
      "name": "JD.com",
      "signal_date": "2025-06-13",
      "entry_date": "2025-06-16",
      "entry_price": 129.0,
      "exit_date": "2025-07-29",
      "exit_price": 130.4,
      "stop_loss": 118.85,
      "target_price": 179.0,
      "exit_reason": "max_hold",
      "holding_days": 43,
      "pnl_pct": 1.09,
      "confidence": 0.8,
      "risk_reward": 4.93
    },
    {
      "ticker": "0968.HK",
      "name": "Xinyi Solar",
      "signal_date": "2025-07-07",
      "entry_date": "2025-07-08",
      "entry_price": 2.73,
      "exit_date": "2025-08-19",
      "exit_price": 3.25,
      "stop_loss": 2.19,
      "target_price": 3.62,
      "exit_reason": "max_hold",
      "holding_days": 42,
      "pnl_pct": 19.05,
      "confidence": 0.67,
      "risk_reward": 1.64
    },
    {
      "ticker": "0175.HK",
      "name": "Geely Auto",
      "signal_date": "2025-08-01",
      "entry_date": "2025-08-04",
      "entry_price": 17.61,
      "exit_date": "2025-09-15",
      "exit_price": 18.46,
      "stop_loss": 15.21,
      "target_price": 20.84,
      "exit_reason": "max_hold",
      "holding_days": 42,
      "pnl_pct": 4.83,
      "confidence": 0.55,
      "risk_reward": 1.34
    },
    {
      "ticker": "9961.HK",
      "name": "Trip.com",
      "signal_date": "2025-08-01",
      "entry_date": "2025-08-04",
      "entry_price": 482.0,
      "exit_date": "2025-08-28",
      "exit_price": 543.0,
      "stop_loss": 426.82,
      "target_price": 543.0,
      "exit_reason": "target",
      "holding_days": 24,
      "pnl_pct": 12.66,
      "confidence": 0.55,
      "risk_reward": 1.11
    },
    {
      "ticker": "1876.HK",
      "name": "Budweiser APAC",
      "signal_date": "2025-10-30",
      "entry_date": "2025-10-31",
      "entry_price": 8.0,
      "exit_date": "2025-11-05",
      "exit_price": 7.68,
      "stop_loss": 7.68,
      "target_price": 8.82,
      "exit_reason": "stop_loss",
      "holding_days": 5,
      "pnl_pct": -4.0,
      "confidence": 0.78,
      "risk_reward": 2.56
    },
    {
      "ticker": "0316.HK",
      "name": "Orient Overseas",
      "signal_date": "2025-10-21",
      "entry_date": "2025-10-22",
      "entry_price": 126.7,
      "exit_date": "2025-12-04",
      "exit_price": 133.7,
      "stop_loss": 117.7,
      "target_price": 147.5,
      "exit_reason": "max_hold",
      "holding_days": 43,
      "pnl_pct": 5.52,
      "confidence": 0.7,
      "risk_reward": 2.31
    },
    {
      "ticker": "1093.HK",
      "name": "CSPC Pharmaceutical",
      "signal_date": "2025-11-21",
      "entry_date": "2025-11-24",
      "entry_price": 7.46,
      "exit_date": "2026-01-08",
      "exit_price": 9.09,
      "stop_loss": 7.06,
      "target_price": 11.48,
      "exit_reason": "max_hold",
      "holding_days": 45,
      "pnl_pct": 21.85,
      "confidence": 0.8,
      "risk_reward": 9.95
    },
    {
      "ticker": "0960.HK",
      "name": "Longfor Group",
      "signal_date": "2025-11-20",
      "entry_date": "2025-11-21",
      "entry_price": 9.66,
      "exit_date": "2025-12-16",
      "exit_price": 9.08,
      "stop_loss": 9.08,
      "target_price": 12.1,
      "exit_reason": "stop_loss",
      "holding_days": 25,
      "pnl_pct": -6.0,
      "confidence": 0.8,
      "risk_reward": 4.22
    },
    {
      "ticker": "2007.HK",
      "name": "Country Garden",
      "signal_date": "2025-12-08",
      "entry_date": "2025-12-09",
      "entry_price": 0.5,
      "exit_date": "2025-12-18",
      "exit_price": 0.47,
      "stop_loss": 0.47,
      "target_price": 0.69,
      "exit_reason": "stop_loss",
      "holding_days": 9,
      "pnl_pct": -6.0,
      "confidence": 0.8,
      "risk_reward": 6.63
    },
    {
      "ticker": "9961.HK",
      "name": "Trip.com",
      "signal_date": "2026-01-29",
      "entry_date": "2026-01-30",
      "entry_price": 484.8,
      "exit_date": "2026-02-12",
      "exit_price": 441.6,
      "stop_loss": 441.6,
      "target_price": 609.0,
      "exit_reason": "stop_loss",
      "holding_days": 13,
      "pnl_pct": -8.91,
      "confidence": 0.9,
      "risk_reward": 2.88
    },
    {
      "ticker": "0981.HK",
      "name": "SMIC",
      "signal_date": "2026-01-20",
      "entry_date": "2026-01-21",
      "entry_price": 73.45,
      "exit_date": "2026-03-04",
      "exit_price": 60.91,
      "stop_loss": 60.91,
      "target_price": 86.91,
      "exit_reason": "stop_loss",
      "holding_days": 42,
      "pnl_pct": -17.07,
      "confidence": 0.65,
      "risk_reward": 1.07
    },
    {
      "ticker": "2018.HK",
      "name": "AAC Technologies",
      "signal_date": "2026-03-20",
      "entry_date": "2026-03-23",
      "entry_price": 31.84,
      "exit_date": "2026-04-27",
      "exit_price": 39.5,
      "stop_loss": 30.93,
      "target_price": 48.56,
      "exit_reason": "end_of_data",
      "holding_days": 35,
      "pnl_pct": 24.06,
      "confidence": 0.95,
      "risk_reward": 18.4
    },
    {
      "ticker": "1177.HK",
      "name": "Sino Biopharmaceutical",
      "signal_date": "2026-03-23",
      "entry_date": "2026-03-24",
      "entry_price": 5.78,
      "exit_date": "2026-03-27",
      "exit_price": 5.48,
      "stop_loss": 5.48,
      "target_price": 8.54,
      "exit_reason": "stop_loss",
      "holding_days": 3,
      "pnl_pct": -5.19,
      "confidence": 0.8,
      "risk_reward": 9.25
    }
  ]
}