{"results": [{"sym": "0728.HK", "name": "中国电信", "price": 4.89, "daily": "空头", "weekly": "空头", "monthly": "盘整", "kangbo": "盘整期", "kangbo_desc": "方向不明, 等待趋势确认", "eight_year": "4年上行段 (高位)", "support": 4.45, "resistance": 4.9, "long_support": 2.04, "vol_pct": 12.9, "price_pct": -4.7, "divergence": false, "warning": "", "signals": [{"type": "假突破", "tf": "weekly", "conf": 0.81, "quality": "呬爛面", "neckline": 2.21, "entry": 2.21, "stop": 2.39, "target": 1.82, "target2": 1.58, "rr": 2.1, "desc": "⭐ 周线假突破! | 前高 2.28 跌破颈线 2.21"}, {"type": "真突破", "tf": "daily", "conf": 0.95, "quality": "呬爛面", "neckline": 5.71, "entry": 5.92, "stop": 5.54, "target": 6.55, "target2": 6.94, "rr": 1.6, "desc": "真突破: 突破前高 5.71 站稳 4天 (量价齐升)"}, {"type": "真突破", "tf": "daily", "conf": 0.95, "quality": "呬爛面", "neckline": 4.57, "entry": 4.65, "stop": 4.44, "target": 5.16, "target2": 5.48, "rr": 2.4, "desc": "真突破: 突破前高 4.57 站稳 4天 (量价齐升)"}, {"type": "真突破", "tf": "daily", "conf": 0.95, "quality": "呬爛面", "neckline": 4.12, "entry": 4.29, "stop": 3.99, "target": 4.74, "target2": 5.02, "rr": 1.5, "desc": "真突破: 突破前高 4.12 站稳 5天 (量价齐升)"}, {"type": "真突破", "tf": "daily", "conf": 0.95, "quality": "呬爛面", "neckline": 3.85, "entry": 4.04, "stop": 3.73, "target": 4.81, "target2": 5.28, "rr": 2.5, "desc": "真突破: 突破前高 3.85 站稳 4天 (量价齐升)"}, {"type": "真突破", "tf": "daily", "conf": 0.95, "quality": "呬爛面", "neckline": 3.72, "entry": 3.93, "stop": 3.61, "target": 4.56, "target2": 4.94, "rr": 2.0, "desc": "真突破: 突破前高 3.72 站稳 4天 (量价齐升)"}], "signal_count": 6, "real_count": 0, "bluff_count": 6}, {"sym": "0788.HK", "name": "中国铁塔", "price": 10.98, "daily": "盘整", "weekly": "盘整", "monthly": "多头", "kangbo": "盘整期", "kangbo_desc": "方向不明, 等待趋势确认", "eight_year": "4年上行段 (高位)", "support": 10.81, "resistance": 11.39, "long_support": 6.17, "vol_pct": 16.1, "price_pct": -1.9, "divergence": false, "warning": "", "signals": [{"type": "月线缩量见底", "tf": "monthly", "conf": 0.79, "quality": "基本面", "neckline": 8.42, "entry": 8.51, "stop": 8.0, "target": 10.21, "target2": 11.76, "rr": 3.0, "desc": "🟢 月线缩量见底: 量比 0.4x, 低位 6% → 蔡森: 卖压枯竭, 底部区域"}, {"type": "破底翻", "tf": "weekly", "conf": 0.81, "quality": "呬爛面", "neckline": 7.42, "entry": 7.42, "stop": 6.72, "target": 8.93, "target2": 7.98, "rr": 2.2, "desc": "⭐ 周线破底翻! 量先价行上档无压 | 支撑 7.08 → 颈线 7.42"}, {"type": "假突破", "tf": "weekly", "conf": 0.82, "quality": "呬爛面", "neckline": 8.55, "entry": 8.55, "stop": 9.26, "target": 6.81, "target2": 5.74, "rr": 2.5, "desc": "⭐ 周线假突破! | 前高 8.82 跌破颈线 8.55"}, {"type": "假突破", "tf": "daily", "conf": 1.0, "quality": "呬爛面", "neckline": 8.17, "entry": 8.17, "stop": 8.72, "target": 5.9, "target2": 4.5, "rr": 4.1, "desc": "低档假突破: 突破前高 8.47 后跌回颈线 8.17 (量价背离)"}, {"type": "假突破", "tf": "daily", "conf": 1.0, "quality": "呬爛面", "neckline": 8.29, "entry": 8.29, "stop": 8.72, "target": 6.02, "target2": 4.62, "rr": 5.3, "desc": "低档假突破: 突破前高 8.47 后跌回颈线 8.29 (量价背离)"}, {"type": "真突破", "tf": "daily", "conf": 0.95, "quality": "呬爛面", "neckline": 12.48, "entry": 12.78, "stop": 12.11, "target": 14.03, "target2": 14.81, "rr": 1.9, "desc": "真突破: 突破前高 12.48 站稳 4天 (量价齐升)"}, {"type": "回踩支撑", "tf": "daily", "conf": 0.95, "quality": "基本面", "neckline": 11.45, "entry": 11.47, "stop": 10.57, "target": 13.27, "target2": 12.31, "rr": 2.0, "desc": "回踩支撑: 价格回踩MA20(11.45)后反弹, 多头趋势确认 (放量反弹)"}, {"type": "回踩支撑", "tf": "daily", "conf": 0.95, "quality": "基本面", "neckline": 11.33, "entry": 11.47, "stop": 10.55, "target": 13.3, "target2": 12.31, "rr": 2.0, "desc": "回踩支撑: 价格回踩MA20(11.33)后反弹, 多头趋势确认 (放量反弹)"}], "signal_count": 8, "real_count": 3, "bluff_count": 5}, {"sym": "0836.HK", "name": "华润电力", "price": 18.85, "daily": "盘整", "weekly": "盘整", "monthly": "多头", "kangbo": "盘整期", "kangbo_desc": "方向不明, 等待趋势确认", "eight_year": "4年上行段 (高位)", "support": 18.36, "resistance": 19.76, "long_support": 10.77, "vol_pct": -6.6, "price_pct": -3.0, "divergence": false, "warning": "", "signals": [{"type": "假突破", "tf": "weekly", "conf": 0.95, "quality": "呬爛面", "neckline": 18.28, "entry": 18.28, "stop": 19.79, "target": 8.78, "target2": 2.9, "rr": 6.3, "desc": "⭐ 周线假突破! | 前高 18.85 跌破颈线 18.28"}, {"type": "假突破", "tf": "daily", "conf": 1.0, "quality": "呬爛面", "neckline": 19.58, "entry": 19.58, "stop": 20.46, "target": 14.98, "target2": 12.13, "rr": 5.3, "desc": "高档假突破: 突破前高 19.86 后跌回颈线 19.58 (量价背离)"}, {"type": "假突破", "tf": "daily", "conf": 1.0, "quality": "呬爛面", "neckline": 14.4, "entry": 14.4, "stop": 15.52, "target": 10.32, "target2": 7.8, "rr": 3.6, "desc": "低档假突破: 突破前高 15.07 后跌回颈线 14.40 (量价背离)"}, {"type": "假突破", "tf": "daily", "conf": 1.0, "quality": "呬爛面", "neckline": 12.12, "entry": 12.12, "stop": 12.84, "target": 9.21, "target2": 7.42, "rr": 4.0, "desc": "低档假突破: 突破前高 12.47 后跌回颈线 12.12 (量价背离)"}, {"type": "假突破", "tf": "daily", "conf": 1.0, "quality": "呬爛面", "neckline": 21.99, "entry": 21.99, "stop": 24.39, "target": 11.65, "target2": 5.26, "rr": 4.3, "desc": "低档假突破: 突破前高 23.68 后跌回颈线 21.99 (量价背离)"}, {"type": "假突破", "tf": "daily", "conf": 1.0, "quality": "呬爛面", "neckline": 21.4, "entry": 21.4, "stop": 22.69, "target": 13.68, "target2": 8.91, "rr": 6.0, "desc": "高档假突破: 突破前高 22.03 后跌回颈线 21.40 (量价背离)"}], "signal_count": 6, "real_count": 0, "bluff_count": 6}, {"sym": "0916.HK", "name": "龙源电力", "price": 6.26, "daily": "空头", "weekly": "盘整", "monthly": "空头", "kangbo": "盘整期", "kangbo_desc": "方向不明, 等待趋势确认", "eight_year": "4年下行段 (低位)", "support": 6.14, "resistance": 6.28, "long_support": 5.4, "vol_pct": 8.8, "price_pct": -22.0, "divergence": false, "warning": "", "signals": [{"type": "假突破", "tf": "daily", "conf": 1.0, "quality": "呬爛面", "neckline": 16.36, "entry": 16.36, "stop": 17.69, "target": 12.26, "target2": 9.73, "rr": 3.1, "desc": "低档假突破: 突破前高 17.18 后跌回颈线 16.36 (量价背离)"}, {"type": "假突破", "tf": "daily", "conf": 1.0, "quality": "呬爛面", "neckline": 6.34, "entry": 6.34, "stop": 6.65, "target": 5.22, "target2": 4.52, "rr": 3.6, "desc": "低档假突破: 突破前高 6.45 后跌回颈线 6.34 (量价背离)"}, {"type": "假突破", "tf": "daily", "conf": 1.0, "quality": "呬爛面", "neckline": 9.83, "entry": 9.83, "stop": 10.63, "target": 7.08, "target2": 5.38, "rr": 3.5, "desc": "低档假突破: 突破前高 10.32 后跌回颈线 9.83 (量价背离)"}, {"type": "假突破", "tf": "daily", "conf": 1.0, "quality": "呬爛面", "neckline": 16.52, "entry": 16.52, "stop": 17.69, "target": 12.93, "target2": 10.7, "rr": 3.1, "desc": "低档假突破: 突破前高 17.18 后跌回颈线 16.52 (量价背离)"}, {"type": "真突破", "tf": "daily", "conf": 0.95, "quality": "呬爛面", "neckline": 7.78, "entry": 8.2, "stop": 7.55, "target": 9.34, "target2": 10.05, "rr": 1.8, "desc": "真突破: 突破前高 7.78 站稳 5天 (量价齐升)"}], "signal_count": 5, "real_count": 0, "bluff_count": 5}, {"sym": "1880.HK", "name": "中国中免", "price": 66.05, "daily": "空头", "weekly": "盘整", "monthly": "盘整", "kangbo": "上行期 (繁荣)", "kangbo_desc": "量价齐升, 康波上行 → 蔡森: 顺势做多", "eight_year": "未知", "support": 63.62, "resistance": 66.32, "long_support": 42.45, "vol_pct": -47.5, "price_pct": -6.5, "divergence": false, "warning": "", "signals": [{"type": "月线缩量见底", "tf": "monthly", "conf": 0.75, "quality": "基本面", "neckline": 36.87, "entry": 45.3, "stop": 35.03, "target": 54.36, "target2": 62.61, "rr": 3.0, "desc": "🟢 月线缩量见底: 量比 0.4x, 低位 19% → 蔡森: 卖压枯竭, 底部区域"}, {"type": "破底翻", "tf": "weekly", "conf": 0.95, "quality": "呬爛面", "neckline": 68.29, "entry": 68.29, "stop": 62.26, "target": 102.19, "target2": 72.75, "rr": 5.6, "desc": "⭐ 周线破底翻! 量先价行上档无压 | 支撑 65.54 → 颈线 68.29"}, {"type": "假突破", "tf": "daily", "conf": 1.0, "quality": "呬爛面", "neckline": 71.13, "entry": 71.13, "stop": 75.55, "target": 44.39, "target2": 27.87, "rr": 6.0, "desc": "低档假突破: 突破前高 73.35 后跌回颈线 71.13 (量价背离)"}, {"type": "假突破", "tf": "daily", "conf": 1.0, "quality": "呬爛面", "neckline": 100.96, "entry": 100.96, "stop": 109.18, "target": 58.96, "target2": 33.0, "rr": 5.1, "desc": "低档假突破: 突破前高 106.00 后跌回颈线 100.96 (量价背离)"}, {"type": "假突破", "tf": "daily", "conf": 1.0, "quality": "呬爛面", "neckline": 80.54, "entry": 80.54, "stop": 85.55, "target": 61.74, "target2": 50.12, "rr": 3.8, "desc": "低档假突破: 突破前高 83.06 后跌回颈线 80.54 (量价背离)"}, {"type": "假突破", "tf": "daily", "conf": 1.0, "quality": "呬爛面", "neckline": 236.07, "entry": 236.07, "stop": 267.31, "target": 122.47, "target2": 52.27, "rr": 3.6, "desc": "低档假突破: 突破前高 259.53 后跌回颈线 236.07 (量价背离)"}, {"type": "真突破", "tf": "daily", "conf": 0.95, "quality": "呬爛面", "neckline": 66.12, "entry": 70.49, "stop": 64.14, "target": 84.0, "target2": 92.36, "rr": 2.1, "desc": "真突破: 突破前高 66.12 站稳 4天 (量价齐升)"}], "signal_count": 7, "real_count": 1, "bluff_count": 6}, {"sym": "2050.HK", "name": "三一国际", "price": 31.72, "daily": "盘整", "weekly": "盘整", "monthly": "盘整", "kangbo": "未知", "kangbo_desc": "", "eight_year": "未知", "support": null, "resistance": null, "long_support": null, "vol_pct": -37.0, "price_pct": 4.2, "divergence": false, "warning": "", "signals": [{"type": "假突破", "tf": "daily", "conf": 1.0, "quality": "呬爛面", "neckline": 38.88, "entry": 38.88, "stop": 41.24, "target": 30.17, "target2": 24.79, "rr": 3.7, "desc": "低档假突破: 突破前高 40.04 后跌回颈线 38.88 (量价背离)"}, {"type": "假突破", "tf": "daily", "conf": 1.0, "quality": "呬爛面", "neckline": 43.82, "entry": 43.82, "stop": 46.84, "target": 26.81, "target2": 16.3, "rr": 5.6, "desc": "低档假突破: 突破前高 45.48 后跌回颈线 43.82 (量价背离)"}, {"type": "真突破", "tf": "daily", "conf": 0.95, "quality": "呬爛面", "neckline": 38.41, "entry": 39.74, "stop": 37.26, "target": 46.82, "target2": 51.19, "rr": 2.9, "desc": "真突破: 突破前高 38.41 站稳 5天 (量价齐升)"}, {"type": "反弹无力", "tf": "daily", "conf": 0.9, "quality": "呬爛面", "neckline": 34.17, "entry": 33.17, "stop": 35.2, "target": 29.06, "target2": 26.52, "rr": 2.0, "desc": "反弹无力: 价格反弹至MA20(34.17)但缩量无法突破, 空头趋势"}, {"type": "反弹无力", "tf": "daily", "conf": 0.9, "quality": "呬爛面", "neckline": 34.74, "entry": 33.87, "stop": 35.78, "target": 29.18, "target2": 26.29, "rr": 2.4, "desc": "反弹无力: 价格反弹至MA20(34.74)但缩量无法突破, 空头趋势"}], "signal_count": 5, "real_count": 0, "bluff_count": 5}, {"sym": "2318.HK", "name": "中国平安", "price": 60.9, "daily": "空头", "weekly": "盘整", "monthly": "多头", "kangbo": "盘整期", "kangbo_desc": "方向不明, 等待趋势确认", "eight_year": "4年上行段 (高位)", "support": 53.73, "resistance": null, "long_support": 26.18, "vol_pct": 7.0, "price_pct": -3.9, "divergence": false, "warning": "", "signals": [{"type": "假突破", "tf": "weekly", "conf": 0.82, "quality": "呬爛面", "neckline": 50.41, "entry": 50.41, "stop": 54.57, "target": 40.37, "target2": 34.17, "rr": 2.4, "desc": "⭐ 周线假突破! | 前高 51.97 跌破颈线 50.41"}, {"type": "破底翻", "tf": "weekly", "conf": 0.84, "quality": "呬爛面", "neckline": 44.64, "entry": 44.64, "stop": 41.06, "target": 54.61, "target2": 46.93, "rr": 2.8, "desc": "⭐ 周线破底翻! 量先价行上档无压 | 支撑 43.22 → 颈线 44.64"}, {"type": "假突破", "tf": "daily", "conf": 1.0, "quality": "呬爛面", "neckline": 51.2, "entry": 51.2, "stop": 53.65, "target": 37.75, "target2": 29.43, "rr": 5.5, "desc": "高档假突破: 突破前高 52.09 后跌回颈线 51.20 (量价背离)"}, {"type": "假突破", "tf": "daily", "conf": 1.0, "quality": "呬爛面", "neckline": 34.37, "entry": 34.37, "stop": 36.02, "target": 25.72, "target2": 20.37, "rr": 5.2, "desc": "低档假突破: 突破前高 34.97 后跌回颈线 34.37 (量价背离)"}, {"type": "假突破", "tf": "daily", "conf": 1.0, "quality": "呬爛面", "neckline": 38.03, "entry": 38.03, "stop": 40.45, "target": 29.98, "target2": 25.01, "rr": 3.3, "desc": "低档假突破: 突破前高 39.27 后跌回颈线 38.03 (量价背离)"}, {"type": "假突破", "tf": "daily", "conf": 1.0, "quality": "呬爛面", "neckline": 48.41, "entry": 48.41, "stop": 51.35, "target": 38.25, "target2": 31.97, "rr": 3.5, "desc": "低档假突破: 突破前高 49.85 后跌回颈线 48.41 (量价背离)"}, {"type": "真突破", "tf": "daily", "conf": 0.95, "quality": "呬爛面", "neckline": 64.02, "entry": 65.2, "stop": 62.1, "target": 73.67, "target2": 78.9, "rr": 2.7, "desc": "真突破: 突破前高 64.02 站稳 5天 (量价齐升)"}], "signal_count": 7, "real_count": 0, "bluff_count": 7}, {"sym": "GC=F", "name": "黄金期货", "price": 4817.8, "daily": "盘整", "weekly": "多头", "monthly": "多头", "kangbo": "盘整期", "kangbo_desc": "方向不明, 等待趋势确认", "eight_year": "4年上行段 (高位)", "support": 3386.0, "resistance": null, "long_support": 1617.75, "vol_pct": 517.6, "price_pct": 5.4, "divergence": false, "warning": "", "signals": [{"type": "月线爆量翻黑", "tf": "monthly", "conf": 0.79, "quality": "基本面", "neckline": 2789.0, "entry": 2657.0, "stop": 2928.45, "target": 2258.45, "target2": 1992.75, "rr": 2.5, "desc": "🔴 月线爆量翻黑: 量比 4.1x, 高位 85% 阴线 → 蔡森: 月线级别顶部信号, 重大卖压"}, {"type": "月线爆量翻黑", "tf": "monthly", "conf": 0.56, "quality": "基本面", "neckline": 2130.2, "entry": 2048.4, "stop": 2236.71, "target": 1741.14, "target2": 1536.3, "rr": 2.5, "desc": "🔴 月线爆量翻黑: 量比 2.4x, 高位 75% 阴线 → 蔡森: 月线级别顶部信号, 重大卖压"}, {"type": "月线爆量翻黑", "tf": "monthly", "conf": 0.6, "quality": "基本面", "neckline": 2072.0, "entry": 1963.9, "stop": 2175.6, "target": 1669.32, "target2": 1472.93, "rr": 2.5, "desc": "🔴 月线爆量翻黑: 量比 2.7x, 高位 76% 阴线 → 蔡森: 月线级别顶部信号, 重大卖压"}, {"type": "月线缩量见底", "tf": "monthly", "conf": 0.88, "quality": "基本面", "neckline": 1620.4, "entry": 1635.9, "stop": 1539.38, "target": 1963.08, "target2": 2260.81, "rr": 3.0, "desc": "🟢 月线缩量见底: 量比 0.1x, 低位 3% → 蔡森: 卖压枯竭, 底部区域"}, {"type": "假突破", "tf": "weekly", "conf": 0.8, "quality": "呬爛面", "neckline": 2326.45, "entry": 2326.45, "stop": 2518.32, "target": 1926.35, "target2": 1679.09, "rr": 2.1, "desc": "⭐ 周线假突破! (量价背离) | 前高 2398.40 跌破颈线 2326.45"}, {"type": "假突破", "tf": "daily", "conf": 1.0, "quality": "呬爛面", "neckline": 4462.06, "entry": 4462.06, "stop": 4664.97, "target": 3482.36, "target2": 2876.91, "rr": 4.8, "desc": "高档假突破: 突破前高 4529.10 后跌回颈线 4462.06 (量价背离)"}, {"type": "假突破", "tf": "daily", "conf": 1.0, "quality": "呬爛面", "neckline": 4146.34, "entry": 4146.34, "stop": 4466.49, "target": 3103.14, "target2": 2458.44, "rr": 3.3, "desc": "高档假突破: 突破前高 4336.40 后跌回颈线 4146.34 (量价背离)"}, {"type": "假突破", "tf": "daily", "conf": 1.0, "quality": "呬爛面", "neckline": 3371.68, "entry": 3371.68, "stop": 3542.38, "target": 2823.48, "target2": 2484.69, "rr": 3.2, "desc": "高档假突破: 突破前高 3439.20 后跌回颈线 3371.68 (量价背离)"}, {"type": "假突破", "tf": "daily", "conf": 1.0, "quality": "呬爛面", "neckline": 3327.68, "entry": 3327.68, "stop": 3508.39, "target": 2758.28, "target2": 2406.39, "rr": 3.1, "desc": "高档假突破: 突破前高 3406.20 后跌回颈线 3327.68 (量价背离)"}, {"type": "真突破", "tf": "daily", "conf": 0.95, "quality": "呬爛面", "neckline": 4875.95, "entry": 5318.4, "stop": 4729.67, "target": 6246.65, "target2": 6820.31, "rr": 1.6, "desc": "真突破: 突破前高 4875.95 站稳 5天 (量价齐升)"}], "signal_count": 10, "real_count": 4, "bluff_count": 6}, {"sym": "GLD", "name": "黄金ETF GLD", "price": 440.08, "daily": "盘整", "weekly": "多头", "monthly": "多头", "kangbo": "盘整期", "kangbo_desc": "方向不明, 等待趋势确认", "eight_year": "4年上行段 (高位)", "support": 314.2, "resistance": null, "long_support": 150.8, "vol_pct": 7.1, "price_pct": 3.2, "divergence": false, "warning": "", "signals": [{"type": "假突破", "tf": "weekly", "conf": 0.8, "quality": "呬爛面", "neckline": 216.95, "entry": 216.95, "stop": 234.84, "target": 179.63, "target2": 156.57, "rr": 2.1, "desc": "⭐ 周线假突破! | 前高 223.66 跌破颈线 216.95"}, {"type": "假突破", "tf": "daily", "conf": 1.0, "quality": "呬爛面", "neckline": 411.67, "entry": 411.67, "stop": 429.24, "target": 357.25, "target2": 323.61, "rr": 3.1, "desc": "高档假突破: 突破前高 416.74 后跌回颈线 411.67 (量价背离)"}, {"type": "假突破", "tf": "daily", "conf": 1.0, "quality": "呬爛面", "neckline": 220.27, "entry": 220.27, "stop": 231.3, "target": 183.71, "target2": 161.11, "rr": 3.3, "desc": "高档假突破: 突破前高 224.56 后跌回颈线 220.27 (量价背离)"}, {"type": "真突破", "tf": "daily", "conf": 0.95, "quality": "呬爛面", "neckline": 448.5, "entry": 476.1, "stop": 435.04, "target": 539.18, "target2": 578.16, "rr": 1.5, "desc": "真突破: 突破前高 448.50 站稳 4天 (量价齐升)"}, {"type": "真突破", "tf": "daily", "conf": 0.95, "quality": "呬爛面", "neckline": 424.83, "entry": 464.7, "stop": 412.08, "target": 553.91, "target2": 609.04, "rr": 1.7, "desc": "真突破: 突破前高 424.83 站稳 5天 (量价齐升)"}, {"type": "真突破", "tf": "daily", "conf": 0.95, "quality": "呬爛面", "neckline": 419.09, "entry": 458.0, "stop": 406.51, "target": 541.47, "target2": 593.05, "rr": 1.6, "desc": "真突破: 突破前高 419.09 站稳 5天 (量价齐升)"}], "signal_count": 6, "real_count": 0, "bluff_count": 6}], "date": "2026-04-17 12:43"}